[1,["f6SJZOjTJB/JrJeh5xTdF7","feeOqqnkpEALObbpFtsmSS@73b7f","feeOqqnkpEALObbpFtsmSS@7598a","feeOqqnkpEALObbpFtsmSS@dcad8","feeOqqnkpEALObbpFtsmSS@7fd11","feeOqqnkpEALObbpFtsmSS@7ea6b","feeOqqnkpEALObbpFtsmSS@30732","feeOqqnkpEALObbpFtsmSS@8b471","feeOqqnkpEALObbpFtsmSS@8d41b","feeOqqnkpEALObbpFtsmSS@f1394"],["_parent","node","mainTexture","_effectAsset","_mesh","_skeleton","root","data","_defaultClip"],[["cc.Node",["_name","_prefab","_parent","_children","_lpos","_lrot","_euler","_components","_lscale"],2,4,1,2,5,5,5,9,5],["cc.Node",["_name","_parent","_children","_prefab","_lpos","_lrot","_euler","_lscale"],2,1,9,4,5,5,5,5],["cc.Node",["_name","_children","_prefab","_lpos","_lrot","_euler","_parent"],2,12,4,5,5,5,1],["cc.Skeleton",["_name","_hash","_joints","_bindposes"],0,12],["cc.Mesh",["_native","_hash","_struct"],1,11],["cc.Material",["_name","_states","_defines","_props"],0,12],["cc.Prefab",["_name"],2],["cc.SkeletalAnimation",["node","__prefab","_clips","_defaultClip"],3,1,4,3,6],["cc.CompPrefabInfo",["fileId"],2],["cc.PrefabInfo",["fileId","instance","targetOverrides","nestedPrefabInstanceRoots","root","asset"],-1,1,1],["cc.SkinnedMeshRenderer",["node","__prefab","_materials","bakeSettings","_skinningRoot","_mesh","_skeleton"],3,1,4,3,4,1,6,6],["cc.ModelBakeSettings",[],3]],[[9,0,1,2,3,4,5,5],[0,0,2,3,1,4,5,6,2],[0,0,2,1,4,2],[1,0,1,2,3,4,5,6,2],[0,0,2,3,1,4,5,8,6,2],[2,0,6,1,2,3,4,5,2],[0,0,3,1,4,5,6,2],[0,0,2,1,4,5,6,2],[1,0,1,2,3,4,5,7,6,2],[1,0,1,2,3,4,2],[8,0,2],[3,0,1,2,3,4],[4,0,1,2,3],[5,0,1,2,3,4],[0,0,2,3,1,2],[0,0,2,7,1,2],[10,0,1,2,3,4,5,6,1],[11,1],[6,0,2],[0,0,3,7,1,2],[2,0,1,2,3,4,5,2],[7,0,1,2,3,1]],[[[[11,"Skin-0",374702284,["Group/DeformationSystem/Root_M/Spine1_M/Chest_M/Scapula_L/Shoulder_L/Elbow_L/ElbowPart1_L/Wrist_L/Weapon_M","Group/DeformationSystem/Root_M/Spine1_M/Chest_M/Scapula_L/Shoulder_L/Elbow_L/ElbowPart1_L/Wrist_L/Weapon_M/Weapon_D1_R","Group/DeformationSystem/Root_M/Spine1_M/Chest_M/Scapula_L/Shoulder_L/Elbow_L/ElbowPart1_L/Wrist_L/Weapon_M/Weapon_D1_R/Weapon_D2_R","Group/DeformationSystem/Root_M/Spine1_M/Chest_M/Scapula_L/Shoulder_L/Elbow_L/ElbowPart1_L/Wrist_L/Weapon_M/Weapon_D1_R/Weapon_D2_R/Weapon_D3_R","Group/DeformationSystem/Root_M/Spine1_M/Chest_M/Scapula_L/Shoulder_L/Elbow_L/ElbowPart1_L/Wrist_L/Weapon_M/Weapon_D1_R/Weapon_D2_R/Weapon_D3_R/Weapon_D4_R","Group/DeformationSystem/Root_M/Spine1_M/Chest_M/Scapula_L/Shoulder_L/Elbow_L/ElbowPart1_L/Wrist_L/Weapon_M/Weapon_D1_L","Group/DeformationSystem/Root_M/Spine1_M/Chest_M/Scapula_L/Shoulder_L/Elbow_L/ElbowPart1_L/Wrist_L/Weapon_M/Weapon_D1_L/Weapon_D2_L","Group/DeformationSystem/Root_M/Spine1_M/Chest_M/Scapula_L/Shoulder_L/Elbow_L/ElbowPart1_L/Wrist_L/Weapon_M/Weapon_D1_L/Weapon_D2_L/Weapon_D3_L","Group/DeformationSystem/Root_M/Spine1_M/Chest_M/Scapula_L/Shoulder_L/Elbow_L/ElbowPart1_L/Wrist_L/Weapon_M/Weapon_D1_L/Weapon_D2_L/Weapon_D3_L/Weapon_D4_L"],[[[7,6.123234262925839e-17,-1,0,0,1,6.123234262925839e-17,0,0,0,0,1,0,-16.4067325592041,-1.004622685937134e-15,0.06349554657936096,1],[7,-0.9999859929084778,-0.005347520112991333,6.548821479818939e-19,0,-0.005347520112991333,0.9999859929084778,-1.2246292501817327e-16,0,-2.4130434157664682e-33,-1.2246471172829639e-16,-1,0,-0.9025061130523682,-16.389598846435547,2.007146424230972e-15,1],[7,-0.9359319806098938,-0.35218098759651184,4.312972984282935e-17,0,-0.35218098759651184,0.9359319806098938,-1.146186058332104e-16,0,1.1629273758165166e-31,-1.2246468525851679e-16,-1,0,3.086681842803955,-15.873324394226074,1.9439213439490692e-15,1],[7,-0.6397759914398193,-0.7685620188713074,9.412165920674251e-17,0,-0.7685620188713074,0.6397759914398193,-7.834992558120214e-17,0,7.681040083417766e-33,-1.22464738198076e-16,-1,0,9.25998592376709,-12.777131080627441,1.564746621594208e-15,1],[7,-0.8373990058898926,-0.5465919971466064,6.693821464231448e-17,0,-0.5465919971466064,0.8373990058898926,-1.0255180755385014e-16,0,-1.4075027287889981e-31,-1.2246467202362698e-16,-1,0,3.850325107574463,-14.57990837097168,1.78552385347191e-15,1],[7,-0.9999859929084778,-0.005347520112991333,0,0,0.005347520112991333,-0.9999859929084778,0,0,0,0,1,0,0.9025061130523682,16.389598846435547,0,1],[7,-0.9359319806098938,-0.35218098759651184,0,0,0.35218098759651184,-0.9359319806098938,0,0,0,0,1,0,-3.086681842803955,15.873324394226074,0,1],[7,-0.6397759914398193,-0.7685620188713074,0,0,0.7685620188713074,-0.6397759914398193,0,0,0,0,1,0,-9.25998592376709,12.777131080627441,0,1],[7,-0.8373990058898926,-0.5465919971466064,0,0,0.5465919971466064,-0.8373990058898926,0,0,0,0,1,0,-3.850325107574463,14.57990837097168,0,1]],8,8,8,8,8,8,8,8,8]]],0,0,[],[],[]],[[[12,".bin",3266719328,[{"primitives":[{"primitiveMode":7,"jointMapIndex":0,"vertexBundelIndices":[0],"indexView":{"offset":130536,"length":12546,"count":6273,"stride":2}}],"vertexBundles":[{"view":{"offset":0,"length":130536,"count":1813,"stride":72},"attributes":[{"name":"a_position","format":32,"isNormalized":false},{"name":"a_normal","format":32,"isNormalized":false},{"name":"a_texCoord","format":21,"isNormalized":false},{"name":"a_tangent","format":44,"isNormalized":false},{"name":"a_joints","format":42,"isNormalized":false},{"name":"a_weights","format":44,"isNormalized":false}]}],"jointMaps":[[0,1,2,3,4,5,6,7,8]]},"minPosition",8,[1,-5.6061110496521,13.786687850952148,-0.2808547019958496],"maxPosition",8,[1,5.606110095977783,17.837923049926758,1.1887871026992798]]],-1],0,0,[],[],[]],[[[13,"TI_tex_weapon_700",[{"rasterizerState":{},"blendState":{"targets":[{}]},"depthStencilState":{}}],[{"USE_ALBEDO_MAP":true,"DCC_APP_NAME":5}],[[[{"albedoScale":0.800000011920929,"emissiveScale":1},"mainColor",8,[4,4294967295],"emissive",8,[4,4278190080],"mainTexture",6,0]],11]]],0,0,[0,0],[2,3],[2,0]],[[[13,"TI_tex_hero_700_D_shared",[{"rasterizerState":{},"blendState":{"targets":[{}]},"depthStencilState":{}}],[{"USE_ALBEDO_MAP":true,"DCC_APP_NAME":5}],[[[{"albedoScale":0.800000011920929,"emissiveScale":1},"mainColor",8,[4,4294967295],"emissive",8,[4,4278190080],"mainTexture",6,0]],11]]],0,0,[0,0],[2,3],[3,0]],[[[12,".bin",2694464231,[{"primitives":[{"primitiveMode":7,"jointMapIndex":0,"vertexBundelIndices":[0],"indexView":{"offset":746136,"length":79476,"count":39738,"stride":2}}],"vertexBundles":[{"view":{"offset":0,"length":746136,"count":10363,"stride":72},"attributes":[{"name":"a_position","format":32,"isNormalized":false},{"name":"a_normal","format":32,"isNormalized":false},{"name":"a_texCoord","format":21,"isNormalized":false},{"name":"a_tangent","format":44,"isNormalized":false},{"name":"a_joints","format":42,"isNormalized":false},{"name":"a_weights","format":44,"isNormalized":false}]}],"jointMaps":[[0,1,2,3,4,6,7,8,9,10,12,13,14,15,17,18,19,20,21,23,24,25,26,27,28,29,30,32,33,34,36,37,38,40,41,42,43,45,46,47,49,51,53,54,55,56,57,58,59,60,62,63,64,66,67,68,70,71,72,73,75,76,77,79,81,83,84,85,86,88,89,90,92,94,96,98,99,100,102,104,106,108,109,110,111,113,115,117,119]]},"minPosition",8,[1,-3.2005722522735596,-8.106231774718253e-8,-4.44752836227417],"maxPosition",8,[1,3.2005722522735596,11.742405891418457,1.2065613269805908]]],-1],0,0,[],[],[]],[[[18,"TI_anim_hero_700_win"],[19,"TI_anim_hero_700_win",[-3],[[21,-2,[10,"5dflXW5JxVPokHcJa8/HZ9"],[6],7]],[0,"4ekFad46BWD5NExdxsG3mW",null,null,null,-1,0]],[6,"Root_M",[-4,-5,-6,-7,-8,-9,-10,-11,-12,-13,-14],[0,"12CzSZ6Bhfl74mpFZkiG80",null,null,null,1,0],[1,-0.6029866933822632,3.540769100189209,0.5582388043403625],[3,0.7326028842183296,0.6564283876628731,0.14244122607071363,0.11002401111020009],[1,-167.2485007546282,-33.35433209257464,83.28818528185671]],[6,"Wrist_L",[-15,-16,-17,-18,-19],[0,"a0LKEAu3ZZ/63I64WoX0up",null,null,null,1,0],[1,-0.7742217183113098,-7.815970051009455e-16,-3.97903933719722e-15],[3,-0.10603377921657217,0.03497131526062854,0.15545391968388933,0.9815130786845928],[1,-13.263241477914958,6.110369271882715,17.322142553479424]],[20,"Head_M",[[[2,"HeadEnd_M",-20,[0,"a5DDm7ZpBScLxitVjyk2j1",null,null,null,1,0],[1,2.066333055496216,-4.831690653990658e-15,-8.526512638538789e-16]],-21,-22,-23],4,1,1,1],[0,"91STIzPj9S97F97Nlyyunn",null,null,null,1,0],[1,0.6597557663917542,-0.00423484668135643,0.0021284057293087244],[3,0.0885947735849176,0.010708615384874368,-0.3624336191509969,0.9277274186737644],[1,13.418029502203552,6.508599356090992,-42.11198098856126]],[6,"Wrist_R",[-24,-25,-26,-27],[0,"9bQuzgdN5eNaNRzKozqZPm",null,null,null,1,0],[1,0.7742217183113098,4.1211477488239685e-15,5.684341970784096e-15],[3,-0.033202740863609755,-0.022654238793891487,-0.033190145657274336,0.998640464679387],[1,-3.896926385758279,-2.725486831700565,-3.714547534952935]],[5,"Weapon_M",3,[[[2,"Weapon_FX_M",-28,[0,"4cnuy0skVY8ZH+nPifoJn/",null,null,null,1,0],[1,1.199410080909729,-5.684341759025859e-16,1.1368683518051719e-15]],-29,-30,-31],4,1,1,1],[0,"92dGjaU0dcpZ0v2RdFlOFZ",null,null,null,1,0],[1,-0.4253954589366913,0.04222074896097183,0.18441873788833618],[3,0.055838070490585395,0.9936746898104274,-0.06636834106645997,-0.071329965779646],[1,7.171513342219698,-172.22224566120263,6.9173732582682295]],[14,"Group",1,[-32,-33,-34],[0,"1ei0E8eqpd3rtOkdafooES",null,null,null,1,0]],[6,"Chest_M",[-35,-36,-37],[0,"b7aebC4BNcVqZCkBrWbX1L",null,null,null,1,0],[1,0.7446105480194092,-9.94759834299305e-16,0],[3,0.06259785435885723,-0.0347173279775473,-0.059690321233032084,0.995647167082227],[1,6.974718157013532,-3.56224404409491,-7.0772505574345175]],[1,"Scapula_R",8,[-38,-39],[0,"72i43l2EJVG7FpJuVlsU8k",null,null,null,1,0],[1,0.8375447988510132,-0.04288633167743683,-0.2534671127796173],[3,-0.31337794401355334,0.6351473278721443,-0.2225581240058595,0.6699626986196364],[1,-11.019043012809966,82.46574680652071,-44.130391066571335]],[6,"Elbow_R",[-40,-41],[0,"a6H+id09dZ1KKzZusUhxNK",null,null,null,1,0],[1,1.1799930334091187,0,-7.95807867439444e-15],[3,0.012437663756595465,-0.06480811423875837,0.4764579451869459,0.8767171946057218],[1,8.70683684262714,-13.139535760850219,56.49375134056346]],[1,"Cup_R",5,[-42,-43],[0,"6f39nwFqJZzK/QbG6ezOAB",null,null,null,1,0],[1,0.26239681243896484,-0.2658108174800873,-0.07606516033411026],[3,-0.006344151059722304,-0.047863132061393206,0.1312452820087537,0.9901734940337716],[1,5.19108603647653e-9,-5.534833161496144,15.100830363636057]],[5,"ArmorShoulder1_R",9,[[[2,"ArmorShoulder1_end_R",-44,[0,"4cZa4IfolRzKkgtL3APG63",null,null,null,1,0],[1,0.6975150108337402,-1.1368683518051719e-15,-1.6342483218943836e-15]],-45],4,1],[0,"03A1ZTk9xTZoxb/fKKf2aU",null,null,null,1,0],[1,0.8777086734771729,0.02872540056705475,0.5980757474899292],[3,0.6861159299559301,0.30771625464092256,-0.16141817195122515,0.6391398994386103],[1,89.62572414339547,39.02834390357221,12.469534265679819]],[1,"Scapula_L",8,[-46,-47],[0,"60Dshmm4pYLL6+mdZyrX6Z",null,null,null,1,0],[1,0.8375447988510132,-0.04288633167743683,0.2534671127796173],[3,-0.5973225652755457,-0.1528513385685163,0.7834938529480379,0.07732789731457078],[1,171.1159836737463,106.74215541891427,17.684478450435826]],[6,"Elbow_L",[-48,-49],[0,"37hvWdwG1eEa5y6oCyWDwZ",null,null,null,1,0],[1,-1.1799930334091187,-1.7053025277077578e-15,-1.7053025277077578e-15],[3,0.010047204896742027,-0.052352302319578534,0.21689169333898678,0.9747390848202144],[1,2.6737398376586494,-6.7402443295166,24.94661507397519]],[1,"Cup_L",3,[-50,-51],[0,"04P7uMIA5fFpIrWind6rOu",null,null,null,1,0],[1,-0.26239681243896484,0.2658108174800873,0.07606516033411026],[3,-0.006344151059722304,-0.047863132061393206,0.1312452820087537,0.9901734940337716],[1,5.19108603647653e-9,-5.534833161496144,15.100830363636057]],[5,"ArmorShoulder1_L",13,[[[2,"ArmorShoulder1_end_L",-52,[0,"61sZ4brxdaa5E5qm8A0UYU",null,null,null,1,0],[1,-0.6975150108337402,5.684341970784096e-15,1.7763568394002505e-15]],-53],4,1],[0,"59m58ffLZaEaME6G9HnGFR",null,null,null,1,0],[1,-0.8777086734771729,-0.02872540056705475,-0.5980757474899292],[3,0.6630594102034529,0.33091604548443043,-0.31157362309329173,0.5947845549222969],[1,94.22211906026223,53.970462046303545,3.910357213187113]],[5,"ArmorHip1_R",2,[[[2,"ArmorHip1_end_R",-54,[0,"7ctpguz1tTKJWKcrB+3k79",null,null,null,1,0],[1,0.5059230327606201,3.97903933719722e-15,8.526512638538789e-16]],-55],4,1],[0,"56Uaef4hdXjYeTBAiDHX3y",null,null,null,1,0],[1,0.6706300377845764,0.03684306517243385,-0.7862652540206909],[3,-0.15216551480545248,-0.6536517635963447,0.6814161431356116,-0.2919881297682621],[1,88.53614244852636,143.05010766621908,-11.47874137119945]],[5,"ArmorHip2_R",17,[[[2,"ArmorHip2_end_R",-56,[0,"31MwVB//JRnqswsimpExOq",null,null,null,1,0],[1,0.45735087990760803,-2.2737367036103438e-15,1.8474110452136247e-15]],-57],4,1],[0,"aahcAFebBbe6erkufrdLT8",null,null,null,1,0],[1,0.548105001449585,0.09074266254901886,-0.00007038248440949246],[3,0.012170008203252449,-0.0027673642206415216,0.040904383499928,0.9990851134943878],[1,1.411131561658688,-0.37512660228811684,4.684366300424277]],[5,"ArmorHip1_L",2,[[[2,"ArmorHip1_end_L",-58,[0,"e4ieNBxxhdc7FNrnvbuqpy",null,null,null,1,0],[1,-0.5059230327606201,-4.5474734072206875e-15,-8.526512638538789e-16]],-59],4,1],[0,"cb0/RwRMpROZioskpcQVTQ",null,null,null,1,0],[1,0.6706300377845764,0.03684306517243385,0.7862652540206909],[3,-0.7270917850147893,0.3901329315849435,0.060158062376210304,0.5617070761420807],[1,-94.27467951684409,37.37240579508712,-29.982964115014305]],[5,"ArmorHip2_L",19,[[[2,"ArmorHip2_end_L",-60,[0,"40/zukhgBaFIWJ0FW4p60O",null,null,null,1,0],[1,-0.45735087990760803,2.842170985392048e-15,-1.2789769751901572e-15]],-61],4,1],[0,"5fIpvN9uddaqeKxDmb3Mga",null,null,null,1,0],[1,-0.548105001449585,-0.09074266254901886,0.00007038248440949246],[3,0.009908221666468162,-0.014034801169045328,0.03275704757841603,0.9993156795194895],[1,1.1899203183689937,-1.6480940946594642,3.737828088703337]],[14,"DeformationSystem",7,[2],[0,"3aCB9fkflcebpT6LH8FVqQ",null,null,null,1,0]],[1,"Spine1_M",2,[8],[0,"31n/GQY8tZE7gwD2gCQ13f",null,null,null,1,0],[1,0.5931563377380371,9.94759834299305e-16,-1.4210854397564648e-16],[3,0.02713060872835472,-0.02315596063103521,0.010276296861189077,0.9993108271604505],[1,3.1362127220370266,-2.6850790277374483,1.1048433305590564]],[1,"Neck_M",8,[4],[0,"1bvVHWuH1bJ7pZO22jPi0m",null,null,null,1,0],[1,1.0162814855575562,-2.415845326995329e-15,0],[3,0.04991560289042118,-0.015313216054690682,0.2481253524422103,0.967319878570464],[1,6.813086249603396,-3.5516717055338773,28.587769771835916]],[4,"HairSide1_R",4,[-62],[0,"42qiO9+eVR15hpRXdB4su4",null,null,null,1,0],[1,1.1679773330688477,-0.7129499912261963,-0.3320003151893616],[3,-0.11032795931992784,-0.009830685355518546,0.9933391236759459,-0.03175664328050583],[1,1.0163958072662354,1.0163958072662354,1.0163958072662354],[1,178.47649281983053,167.27807002879433,-3.492680819474619]],[4,"HairSide2_R",24,[-63],[0,"94duDU0u9b+4RoTxQgZ4//",null,null,null,1,0],[1,0.7639676928520203,-0.1375022828578949,0.12792399525642395],[3,0.9428025603707298,-0.3315532547579513,-0.017248925040468533,-0.029970752455581607],[1,1.0327914953231812,1.0327914953231812,1.0327914953231812],[1,-175.01064991089225,3.8454265517925834,-38.61943002682664]],[4,"HairSide3_R",25,[-64],[0,"38wTEsKdJcQZ0OXEWyI63I",null,null,null,1,0],[1,0.5087440609931946,-0.011239048093557358,-0.0166688933968544],[3,0.1260872641580377,0.022195693269440275,0.09356936881529564,0.9873470140922782],[1,1.0491873025894165,1.0491873025894165,1.0491873025894165],[1,14.44146313261875,1.1809958016344688,10.974264667172841]],[4,"HairSide4_R",26,[-65],[0,"67MOJHMzxY85Ot/fH/Y+CU",null,null,null,1,0],[1,0.41390174627304077,-0.009838835336267948,0.027969306334853172],[3,-0.01790799604878283,0.07883099606609399,-0.16625625190458204,0.9827633674691911],[1,1.0491873025894165,1.0491873025894165,1.0491873025894165],[1,-0.5453632765335273,9.079703017152859,-19.244773127643995]],[8,"HairSide5_R",27,[[7,"HairSide5_end_R",-66,[0,"ecGvo0ghJV0Y8kTTf2cGi4",null,null,null,1,0],[1,0.543697714805603,0.04284004122018814,0.04919767379760742],[3,-0.048588960754707325,0.0016888439211100391,0.03255065489798696,0.9982868904101164],[1,-5.585216450634297,0.3752259450477684,3.7168434160666055]]],[0,"bawdE0qYVWkKcp/qVQ7N1J",null,null,null,1,0],[1,0.337757408618927,-0.0395817868411541,0.03804788738489151],[3,0.06685337330522864,0.025563312335929605,-0.2801701089191669,0.957278357432335],[1,1.0327914953231812,1.0327914953231812,1.0327914953231812],[1,9.683207411649821,5.861038001649652,-32.20726557414299]],[4,"HairBack1_M",4,[-67],[0,"2eDyfj5e5T36uGaGoNcOtW",null,null,null,1,0],[1,1.06399667263031,-0.2912517786026001,-4.1211477488239685e-15],[3,0.849917501274273,-0.5222298320190139,-0.05943117827839399,-0.03720455114002179],[1,0.9916003942489624,0.9916003942489624,0.9916003942489624],[1,-164.4971298178196,17.35891075602764,-62.04087946005015]],[4,"HairBack2_M",29,[-68],[0,"36GR+tWEdeg6KYGe8M0li6",null,null,null,1,0],[1,1.3251595497131348,-0.009457597509026527,-0.01597675122320652],[3,-0.041995044415016336,0.042317397506895386,-0.06383109779610037,0.9961783199141452],[1,0.9832007884979248,0.9832007884979248,0.9832007884979248],[1,-4.5278842195397395,4.567503516950776,-7.511694652355772]],[4,"HairBack3_M",30,[-69],[0,"29VLVniINVCpheyi5hr2OG",null,null,null,1,0],[1,1.4412012100219727,-0.006138850934803486,-0.009454643353819847],[3,-0.02126286968349205,0.060860318473103116,-0.004000879442164651,0.9979117721381308],[1,0.9748011827468872,0.9748011827468872,0.9748011827468872],[1,-2.4043948756311195,6.967313952363756,-0.6058098451731909]],[8,"HairBack4_M",31,[[7,"HairBack4_end_M",-70,[0,"23TKf+v8NWPLhBkgDWhtTr",null,null,null,1,0],[1,1.6664016246795654,0.025424955412745476,0.0650801882147789],[3,-0.13240634146374958,0.042346347895563935,0.020106679195239424,0.9900863947211033],[1,-15.307441424861748,5.1183956523039384,1.6389314350471005]]],[0,"a6WJ9QyZxfyaXCn1Sxl3uY",null,null,null,1,0],[1,1.5956813097000122,-0.015112037770450115,-0.03007841669023037],[3,0.010478917379995501,0.08302301065981825,-0.1057073386379051,0.9908699867034091],[1,0.9832007884979248,0.9832007884979248,0.9832007884979248],[1,2.24504572084688,9.814822282018294,-11.990205431419282]],[4,"HairSide1_L",4,[-71],[0,"52nIriWvtQw58IW4THP5O2",null,null,null,1,0],[1,1.1679773330688477,-0.7129499912261963,0.3320003151893616],[3,-0.004748165936140243,0.14272366052413787,0.04215612140876901,0.9888530088312432],[1,0.9975362420082092,0.9975362420082092,0.9975362420082092],[1,-1.2317393174109157,16.476455400390478,4.7045160769582175]],[4,"HairSide2_L",33,[-72],[0,"6bGHIwa7BRmpItlLbxfTFh",null,null,null,1,0],[1,-0.9466091990470886,0.1487714797258377,0.13499239087104797],[3,0.9197940243802789,-0.39125591573636104,-0.019468048615873746,0.02277622002709348],[1,0.9950725436210632,0.9950725436210632,0.9950725436210632],[1,177.79585546119813,1.4869141952829343,-46.107058046357324]],[4,"HairSide3_L",34,[-73],[0,"b4H0x2tmVUf7wDexttJpAT",null,null,null,1,0],[1,-0.6417011022567749,-0.018090924248099327,0.025704732164740562],[3,-0.02417450612040926,0.20177525512019756,0.19196860711159144,0.9601304044548579],[1,0.9926087856292725,0.9926087856292725,0.9926087856292725],[1,-7.627505301769895,25.154296734222083,21.03107033540764]],[4,"HairSide4_L",35,[-74],[0,"1fU+WW2OpX+4adpWU9Kbn6",null,null,null,1,0],[1,-0.6098780035972595,0.003549040760844946,0.039052341133356094],[3,-0.008990053917725527,0.1618772726933523,-0.15740352692074155,0.9741350302852422],[1,0.9926087856292725,0.9926087856292725,0.9926087856292725],[1,2.0156759161022446,19.189756153941765,-18.033628914905243]],[8,"HairSide5_L",36,[[7,"HairSide5_end_L",-75,[0,"8cqS8TmZRXa5Q34oykbcge",null,null,null,1,0],[1,-0.7055912017822266,0.04998834431171417,0.01019673328846693],[3,0.14275182580776322,-0.011453341529952551,0.007800720055579312,0.9896615006975682],[1,16.424497742842142,-1.4267459137930956,0.6973168092301157]]],[0,"caO2jAC51XHZjuGNuIDJ3g",null,null,null,1,0],[1,-0.5024105906486511,0.017017818987369537,0.07161683589220047],[3,0.01675357645242147,0.11226980224990862,-0.24137532360212594,0.9637700775261641],[1,0.9950725436210632,0.9950725436210632,0.9950725436210632],[1,5.594921083292917,14.658160115543124,-27.48386386619881]],[1,"Shoulder_R",9,[10],[0,"7cICDdb6ZZfb+juSRUIDoh",null,null,null,1,0],[1,0.898816704750061,-2.415845326995329e-15,-2.3874235176150373e-14],[3,-0.028452894992981384,0.33872836127342737,0.07615396222848442,0.9373655125256313],[1,-6.069914625213042,40.11245471744431,7.093713122821853]],[1,"ElbowPart1_R",10,[5],[0,"c27gK4a3lbaIZRW8VXERB4",null,null,null,1,0],[1,0.7742217183113098,1.8474110452136247e-15,6.821210110831031e-15],[3,0.09928220562932262,-2.0667260742233116e-18,-2.071383349250773e-17,0.9950593166466896],[1,11.395676391729731,4.705376746601256e-24,-2.385416058257437e-15]],[1,"MiddleFinger1_R",5,[-76],[0,"f8lKf0hZxVQpTyW+BLvo9M",null,null,null,1,0],[1,0.8413676619529724,-2.700062362007063e-15,1.1368683518051719e-15],[3,0.062422618243432024,0.626400410863192,0.04245604200349725,0.7758372422740843],[1,2.5293465698164614,77.65066621735625,8.284069298912026]],[1,"MiddleFinger2_R",40,[-77],[0,"e6FVzgNF9dCp5q8KDg4PXU",null,null,null,1,0],[1,0.25001049041748047,-1.98951966859861e-15,-1.1368683518051719e-15],[3,0.005410295816828753,0.6438622958487994,-0.011561722293134406,0.7650349006817297],[1,1.3275345856220953,80.17583134285535,-0.6144099554888175]],[3,"MiddleFinger3_R",41,[[2,"MiddleFinger4_R",-78,[0,"06kdBm4R5f8b+NnDdpWvtw",null,null,null,1,0],[1,0.3258524239063263,-2.8421708795129297e-16,5.684341970784096e-15]]],[0,"fd7YTRGtxUaoBIYA4dC0aY",null,null,null,1,0],[1,0.2807110548019409,1.421085492696024e-15,0],[3,0.0038366604373277612,0.5984202661200813,-0.007302864500857028,0.8011398962126038],[1,0.8530593309834859,73.51962717875124,-0.407339840207574]],[1,"ThumbFinger1_R",5,[-79],[0,"34D3ak5u9enJ12vAzaqSZc",null,null,null,1,0],[1,0.21054145693778992,0.2226632535457611,-0.12819522619247437],[3,-0.4555600321541362,-0.015529194969505038,0.3449607816785032,0.8205034797678055],[1,-64.78773371547501,20.769891582929876,35.46686226221689]],[1,"ThumbFinger2_R",43,[-80],[0,"6exG4ujcRU8rZT/UmKX6Bj",null,null,null,1,0],[1,0.33930766582489014,2.2737367036103438e-15,1.1368683518051719e-15],[3,0.02197487245490743,0.4373771778061146,0.003494298729549275,0.8990028360307535],[1,2.0898201341840554,51.8604525907704,1.461509364131926]],[3,"ThumbFinger3_R",44,[[2,"ThumbFinger4_R",-81,[0,"eey4yUxUpVxY6wplfADGXW",null,null,null,1,0],[1,0.32250240445137024,-1.7053025277077578e-15,-8.526512638538789e-16]]],[0,"3dzOY4lxZaiqOWKms/nKdV",null,null,null,1,0],[1,0.26858386397361755,2.2737367036103438e-15,2.2737367036103438e-15],[3,4.4782775402778095e-7,0.3341686199434096,-0.0000013782720604310884,0.9425133067723853],[1,0.000101145258254074,39.043980179664565,-0.00013171036622009475]],[1,"IndexFinger1_R",5,[-82],[0,"d592bG4MdeTKllVcP++MUn",null,null,null,1,0],[1,0.8062770366668701,0.23649950325489044,-0.04458730295300484],[3,-0.09568759748163229,0.6009759274976828,0.049985598507182614,0.7919427114371164],[1,-12.226364733577363,74.16702154249805,-2.053944945598859]],[1,"IndexFinger2_R",46,[-83],[0,"83IVwy7btbX6+nAuhmqZo8",null,null,null,1,0],[1,0.23225468397140503,2.8421708795129297e-16,-6.252776040807564e-15],[3,0.001741546197785504,0.6387532322626026,-0.0029622430304768028,0.7694039903764128],[1,0.3703743818312775,79.39882153629478,-0.13369906023904118]],[3,"IndexFinger3_R",47,[[2,"IndexFinger4_R",-84,[0,"24GlW8Ok1aWrGglpHFzBvA",null,null,null,1,0],[1,0.3123410940170288,2.8421708795129297e-16,3.4106050554155156e-15]]],[0,"5cnD/v7a5ZE5NG+SDeankL",null,null,null,1,0],[1,0.2255726456642151,0,2.2737367036103438e-15],[3,-0.011428007776129678,0.5784179527859327,-0.008265914337672849,0.8156186285227681],[1,-0.5204089414220081,70.67982654641932,-1.5302082360443774]],[1,"PinkyFinger1_R",11,[-85],[0,"daaEe84DxXEYBsCyhotkbo",null,null,null,1,0],[1,0.39715415239334106,-0.2601633369922638,-0.12601713836193085],[3,0.31164693642548175,0.6371376475621621,-0.11982280688009757,0.6946756797433898],[1,37.00633373856932,80.57170937529641,13.335225928523315]],[1,"PinkyFinger2_R",49,[-86],[0,"0959KhT5NUoL9s+yLLeXHH",null,null,null,1,0],[1,0.252667099237442,-2.842170985392048e-15,-3.4106050554155156e-15],[3,0.003363172991849491,0.6634779577440226,0.0001399335015911371,0.7481882577759845],[1,0.27771031571918137,83.13125522289693,0.26769691134323215]],[3,"PinkyFinger3_R",50,[[2,"PinkyFinger4_R",-87,[0,"b6BpEIS15WiaOMdOop4SNm",null,null,null,1,0],[1,0.22195979952812195,-5.684341970784096e-15,3.97903933719722e-15]]],[0,"13vNSoEiNavLYN67r/V3TJ",null,null,null,1,0],[1,0.22058424353599548,1.7053025277077578e-15,5.684341759025859e-16],[3,-4.355005411481018e-16,0.6289004190775123,5.218428725148346e-16,0.777485860247072],[1,-7.640767073924639e-14,77.93808792382417,1.5107634466542826e-14]],[1,"RingFinger1_R",11,[-88],[0,"86AaMHKf5WXIBsb/zMibz+",null,null,null,1,0],[1,0.5497093200683594,-0.10459136962890625,-0.019868269562721252],[3,0.27488442161607807,0.6427858216093882,-0.07585087116731364,0.7109933808650385],[1,30.252744498702196,80.37110233072248,14.212842969372637]],[1,"RingFinger2_R",52,[-89],[0,"d4+n6Z005eroRzpF9xtSRO",null,null,null,1,0],[1,0.2692553400993347,-5.684341759025859e-16,4.5474734072206875e-15],[3,0.0002367366297964569,0.6174531701934528,0.0002073408145754812,0.7866075791546949],[1,0.0066687239887553785,76.26078052065178,0.03543969232729594]],[3,"RingFinger3_R",53,[[2,"RingFinger4_R",-90,[0,"8cQt6RSUdZIYpUkxKl4XBh",null,null,null,1,0],[1,0.25840428471565247,-3.4106050554155156e-15,4.5474734072206875e-15]]],[0,"26w4AzVn9R6ZlZ9XPA1l7f",null,null,null,1,0],[1,0.26181575655937195,1.1368683518051719e-15,-5.115907900760629e-15],[3,3.5378263481012593e-17,0.6022062326321932,-3.5378263481012593e-17,0.798340562278368],[1,5.6778872492070656e-15,74.05614273640758,-7.951384512653196e-16]],[3,"FxArrow_R",10,[[2,"FxArrowEnd_R",-91,[0,"2cHnQfu1lQb5TvlCYWPugS",null,null,null,1,0],[1,0.38238170742988586,-1.7053025277077578e-15,1.1368683518051719e-15]]],[0,"a7LGPPHdVQ7Jjwk2wx7Mlh",null,null,null,1,0],[1,1.9775516986846924,0.02707856334745884,0.01404859684407711],[3,-0.13339630960566393,-0.020396029119685327,0.02902983809041093,0.9904275314631472],[1,-15.282429869919635,-1.8751396411409051,3.6088922628961737]],[3,"ArmorShoulder2_R",12,[[2,"ArmorShoulder2_end_R",-92,[0,"162r9PQEJeaZJIuBpwfvFt",null,null,null,1,0],[1,1.2944813966751099,-1.591615734878888e-14,-5.684341759025859e-16]]],[0,"09mzRpSqZewrULDgsIk/Qj",null,null,null,1,0],[1,0.5390424728393555,0.15026693046092987,1.0658141459917976e-15],[3,-0.08366933320716968,0.04492133778353267,-0.09266669143375927,0.9911581106922982],[1,-9.235627592772722,4.296856308214062,-11.023509709368259]],[1,"Shoulder_L",13,[14],[0,"98ShmUZUhReKdoErH7KuW6",null,null,null,1,0],[1,-0.898816704750061,-2.2737367036103438e-15,2.6147973150310137e-14],[3,0.03605603834909786,0.4571303770486361,-0.07414124979443193,0.8855703560739032],[1,7.601716747639606,54.98073148692272,-5.644162042409243]],[1,"ElbowPart1_L",14,[3],[0,"12Zg3myw5ZtabuLO2Q7zBI",null,null,null,1,0],[1,-0.7742217183113098,-9.592327313926179e-16,-5.115907900760629e-15],[3,0.02940294926638011,-5.5474398603419766e-17,2.0656848743276675e-18,0.9995676398195565],[1,3.3698154684097688,-6.361109326112428e-15,4.969616205398632e-17]],[1,"MiddleFinger1_L",3,[-93],[0,"22r2S1pcJT/ad3ZNtSmdAQ",null,null,null,1,0],[1,-0.8413676619529724,-9.94759834299305e-16,0],[3,0.062422618243432024,0.626400410863192,0.04245604200349725,0.7758372422740843],[1,2.5293465698164614,77.65066621735625,8.284069298912026]],[1,"MiddleFinger2_L",59,[-94],[0,"e76kdfBX9b8JDJu8peAA9A",null,null,null,1,0],[1,-0.25001049041748047,5.684341759025859e-16,1.1368683518051719e-15],[3,0.005410295816828753,0.6438622958487994,-0.011561722293134406,0.7650349006817297],[1,1.3275345856220953,80.17583134285535,-0.6144099554888175]],[3,"MiddleFinger3_L",60,[[2,"MiddleFinger4_L",-95,[0,"eea/qlcC1W45XqRMkDGPsb",null,null,null,1,0],[1,-0.3258524239063263,2.415845326995329e-15,-3.4106050554155156e-15]]],[0,"126vC7tEtZabz98VdiBBpz",null,null,null,1,0],[1,-0.2807110548019409,-4.68958224236391e-15,-1.7053025277077578e-15],[3,0.0038366604373277612,0.5984202661200813,-0.007302864500857028,0.8011398962126038],[1,0.8530593309834859,73.51962717875124,-0.407339840207574]],[1,"ThumbFinger1_L",3,[-96],[0,"f7v7qHDyJRA42A4/cwV3KX",null,null,null,1,0],[1,-0.21054145693778992,-0.2226632535457611,0.12819522619247437],[3,-0.4555600321541362,-0.015529194969505038,0.3449607816785032,0.8205034797678055],[1,-64.78773371547501,20.769891582929876,35.46686226221689]],[1,"ThumbFinger2_L",62,[-97],[0,"7bpWa8vBRaY7eC9tGg4TPw",null,null,null,1,0],[1,-0.33930766582489014,6.821210110831031e-15,-2.2737367036103438e-15],[3,0.02197487245490743,0.4373771778061146,0.003494298729549275,0.8990028360307535],[1,2.0898201341840554,51.8604525907704,1.461509364131926]],[3,"ThumbFinger3_L",63,[[2,"ThumbFinger4_L",-98,[0,"a7l24XffxcZYwgzSS+rWxg",null,null,null,1,0],[1,-0.32250240445137024,0,0]]],[0,"736kkg44pQgZ+rHSbibVhj",null,null,null,1,0],[1,-0.26858386397361755,-2.842170985392048e-15,2.5579539503803143e-15],[3,4.4782775402778095e-7,0.3341686199434096,-0.0000013782720604310884,0.9425133067723853],[1,0.000101145258254074,39.043980179664565,-0.00013171036622009475]],[1,"IndexFinger1_L",3,[-99],[0,"47Z/0L1phVjZTMCSNt7S/o",null,null,null,1,0],[1,-0.8062770366668701,-0.23649950325489044,0.04458730295300484],[3,-0.09568759748163229,0.6009759274976828,0.049985598507182614,0.7919427114371164],[1,-12.226364733577363,74.16702154249805,-2.053944945598859]],[1,"IndexFinger2_L",65,[-100],[0,"3eZXdd1ANd3bsPi5jMRUVc",null,null,null,1,0],[1,-0.23225468397140503,-1.8474110452136247e-15,0],[3,0.001741546197785504,0.6387532322626026,-0.0029622430304768028,0.7694039903764128],[1,0.3703743818312775,79.39882153629478,-0.13369906023904118]],[3,"IndexFinger3_L",66,[[2,"IndexFinger4_L",-101,[0,"7aJiqiAUBTNJt9ZlZqBnXp",null,null,null,1,0],[1,-0.3123410940170288,1.1368683518051719e-15,-5.684341970784096e-15]]],[0,"c44lPgr/FRwaMmeO0JcqKd",null,null,null,1,0],[1,-0.2255726456642151,1.98951966859861e-15,-1.7053025277077578e-15],[3,-0.011428007776129678,0.5784179527859327,-0.008265914337672849,0.8156186285227681],[1,-0.5204089414220081,70.67982654641932,-1.5302082360443774]],[1,"PinkyFinger1_L",15,[-102],[0,"f8r00q1LxUIYyO6rohs/hA",null,null,null,1,0],[1,-0.39715415239334106,0.2601633369922638,0.12601713836193085],[3,0.31164693642548175,0.6371376475621621,-0.11982280688009757,0.6946756797433898],[1,37.00633373856932,80.57170937529641,13.335225928523315]],[1,"PinkyFinger2_L",68,[-103],[0,"ebA/cFB+dcX6C1iCT9SXjZ",null,null,null,1,0],[1,-0.252667099237442,-4.2632563192693945e-16,-3.4106050554155156e-15],[3,0.003363172991849491,0.6634779577440226,0.0001399335015911371,0.7481882577759845],[1,0.27771031571918137,83.13125522289693,0.26769691134323215]],[3,"PinkyFinger3_L",69,[[2,"PinkyFinger4_L",-104,[0,"bbc/MdgR1RaJ9kBqLiuuD2",null,null,null,1,0],[1,-0.22195979952812195,5.684341970784096e-15,8.526512638538789e-16]]],[0,"f20ECkVCJVzYuA++vuSDdu",null,null,null,1,0],[1,-0.22058424353599548,-4.2632563192693945e-16,-1.1368683518051719e-15],[3,-1.2747753421391493e-16,0.6289004190775123,1.4104561258842038e-16,0.777485860247072],[1,-2.1522085303019194e-14,77.93808792382417,3.3793388512324177e-15]],[1,"RingFinger1_L",15,[-105],[0,"11ByoqGh5XH54b9kEy5uUs",null,null,null,1,0],[1,-0.5497093200683594,0.10459136962890625,0.019868269562721252],[3,0.27488442161607807,0.6427858216093882,-0.07585087116731364,0.7109933808650385],[1,30.252744498702196,80.37110233072248,14.212842969372637]],[1,"RingFinger2_L",71,[-106],[0,"a2Dyvi1xlcE5DOO4ZlBZk0",null,null,null,1,0],[1,-0.2692553400993347,1.4210854397564648e-16,-8.526512638538789e-16],[3,0.0002367366297964569,0.6174531701934528,0.0002073408145754812,0.7866075791546949],[1,0.0066687239887553785,76.26078052065178,0.03543969232729594]],[3,"RingFinger3_L",72,[[2,"RingFinger4_L",-107,[0,"72TpufM51YW7xmcxe0uR0s",null,null,null,1,0],[1,-0.25840428471565247,2.5579539503803143e-15,1.6484590995295874e-14]]],[0,"ed2O/4s31cYL/+7Ukw3qWf",null,null,null,1,0],[1,-0.26181575655937195,-7.10542746348012e-16,-7.95807867439444e-15],[3,-9.187167537764785e-17,0.6022062326321932,1.120715782202308e-16,0.798340562278368],[1,-1.6138512286168224e-14,74.05614273640758,3.912796536007747e-15]],[9,"Weapon_String_M",6,[[2,"Weapon_String_end_M",-108,[0,"36uzsHodFbAYTwOMM4ucyg",null,null,null,1,0],[1,-0.24737420678138733,-5.684341759025859e-16,0]]],[0,"33U4WWjP9WsrR7AczQxXGM",null,null,null,1,0],[1,-1.7318426370620728,1.1368683518051719e-15,-5.684341759025859e-16]],[1,"Weapon_D1_R",6,[-109],[0,"17dZV9l4NSo6unMvLjU5vQ",null,null,null,1,0],[1,-0.02219424769282341,0.9901368618011475,0.06349555402994156],[3,0.7052136240654157,0.7089948832202687,6.298702590065259e-17,2.3503318609345518e-17],[1,-6.017835895859422e-13,-179.9999999999994,89.6936099967899]],[1,"Weapon_D2_R",75,[-110],[0,"e0tAdcakZfVqshod5asNf/",null,null,null,1,0],[1,1.7135502099990845,-0.43195945024490356,-1.1368683518051719e-15],[3,5.341749459764473e-17,-1.661948964142805e-17,-0.17634913444978312,0.9843276805915864],[1,6.066752052643835e-15,-8.478749214120011e-16,-20.31435791487413]],[1,"Weapon_D3_R",76,[-111],[0,"007m4OkRNfo6lLLZCGCe/i",null,null,null,1,0],[1,1.347468376159668,-0.18965262174606323,0],[3,-3.747100791537778e-17,-3.316070861875371e-17,-0.2554808312920229,0.9668141211434269],[1,-5.891222321983688e-15,-5.487126800452343e-15,-29.604157046551123]],[3,"Weapon_D4_R",77,[[2,"Weapon_D4_end_R",-112,[0,"29Uqx6T59ZBrlMvRDFsmyt",null,null,null,1,0],[1,1.0781655311584473,-0.013805567286908627,0]]],[0,"3e3HjX2q5TtYxplo3gocvN",null,null,null,1,0],[1,1.2947108745574951,0.02728716842830181,0],[3,2.6931869635734664e-17,7.555359487397326e-18,0.1485983159474042,0.9888976390393474],[1,3.058311669798535e-15,4.159383566626774e-16,17.091411305995482]],[1,"Weapon_D1_L",6,[-113],[0,"e0h3lJG3NcdZAHNaFMf5hh",null,null,null,1,0],[1,-0.02219424769282341,-0.9901368618011475,0.06349555402994156],[3,-8.850105519348075e-17,-6.845515972552031e-17,0.7052136240654157,0.7089948832202687],[1,-3.1010574090508015e-13,2.9738777373563195e-13,89.6936099967899]],[1,"Weapon_D2_L",79,[-114],[0,"17P5ueDLlQQYnXLoqOA342",null,null,null,1,0],[1,-1.7135502099990845,0.43195945024490356,0],[3,-4.485182092085071e-17,6.443050786473737e-17,-0.17634913444978312,0.9843276805915864],[1,-4.006251385569847e-15,6.78299870305547e-15,-20.31435791487413]],[1,"Weapon_D3_L",80,[-115],[0,"1cePVeA85dDrZCFc+n/ZoR",null,null,null,1,0],[1,-1.347468376159668,0.18965262174606323,5.684341759025859e-16],[3,7.473414037535085e-18,5.5441722169257966e-17,-0.2554808312920229,0.9668141211434269],[1,2.8190849242360864e-15,7.316169037779346e-15,-29.604157046551123]],[3,"Weapon_D4_L",81,[[2,"Weapon_D4_end_L",-116,[0,"21M6BUsUNSQoog10hXfqgh",null,null,null,1,0],[1,-1.0781655311584473,0.013805567286908627,0]]],[0,"17JQMWgiBUapocCmiaIK8O",null,null,null,1,0],[1,-1.2947108745574951,-0.02728716842830181,-1.1368683518051719e-15],[3,-2.0548976648724434e-17,-1.434237636743175e-16,0.1485983159474042,0.9888976390393474],[1,1.1889045502765967e-16,-1.663753552715776e-14,17.091411305995482]],[3,"FxArrow_L",14,[[2,"FxArrowEnd_L",-117,[0,"f2pO1MPJxUaoLOYHiwDZyl",null,null,null,1,0],[1,-0.38238170742988586,8.526512638538789e-16,2.2737367036103438e-15]]],[0,"0beiIiJIRY7K+vRSDd7R32",null,null,null,1,0],[1,-1.9775516986846924,-0.02707856334745884,-0.01404859684407711],[3,-0.13339630960566393,-0.020396029119685327,0.02902983809041093,0.9904275314631472],[1,-15.282429869919635,-1.8751396411409051,3.6088922628961737]],[9,"ArmorShoulder2_L",16,[[2,"ArmorShoulder2_end_L",-118,[0,"f4H69K/M1fxYpxIqjbCJSM",null,null,null,1,0],[1,-1.2944813966751099,3.4106050554155156e-15,1.1368683518051719e-15]]],[0,"9f88ATTZNRyIhb8x/+T48x",null,null,null,1,0],[1,-0.5390424728393555,-0.15026693046092987,-1.6342483218943836e-15]],[1,"Hip_R",2,[-119],[0,"abgRGqUu9fMrY/A9smqjU5",null,null,null,1,0],[1,-0.36726757884025574,-0.08317771553993225,-0.47659024596214294],[3,0.07948007698546569,0.6972375147617556,-0.6112587654923608,0.3659309866354449],[1,75.2286683668701,139.82898005103638,-19.66524214017304]],[1,"Knee_R",85,[-120],[0,"069/lFA69WnJxyq3Rvcscn",null,null,null,1,0],[1,1.5957510471343994,1.421085492696024e-15,-1.1368683518051719e-15],[3,7.234456174962783e-18,2.3183585873613452e-17,-0.297884280708279,0.9546019879022416],[1,1.9242395408744424e-15,3.3834456679854577e-15,-34.66114469074869]],[1,"Ankle_R",86,[-121],[0,"c3ZQLN33lcAY9mhxV/My9O",null,null,null,1,0],[1,1.8425168991088867,-2.8421708795129297e-16,5.400124724014126e-15],[3,-0.14381460630203102,0.24070916709609064,0.05675942738331095,0.9582039570431844],[1,-17.648073581220963,28.554625719733863,2.2660215616020816]],[3,"Toes_R",87,[[2,"ToesEnd_R",-122,[0,"c7tNz3OqpVaKrdvAE9jva1",null,null,null,1,0],[1,0.7260444164276123,1.1368683518051719e-15,1.1368683518051719e-15]]],[0,"d3H5GmSqRXbrDdVTtsqOHM",null,null,null,1,0],[1,0.5844144821166992,0.5703486800193787,1.591615734878888e-14],[3,-0.026083946744778482,0.02636718429707208,0.6969574231893452,0.7161527417916711],[1,-69.88761962987044,69.91058785489759,85.47312234057149]],[1,"ClothFront1_M",2,[-123],[0,"daUUbcV01XC7C9yZbZz0k1",null,null,null,1,0],[1,0.3059149980545044,0.638395369052887,-1.4210854397564648e-16],[3,0.23959456727522255,0.9665382642968638,-0.08023902143781998,0.04427105624339438],[1,11.427350064513172,171.98886080578282,27.132520009517027]],[1,"ClothFront2_M",89,[-124],[0,"26UCT3AQxW1qsv9W0pREHb",null,null,null,1,0],[1,0.6866087913513184,5.684341759025859e-16,1.4210854397564648e-16],[3,0.10218969975829348,-0.08709155230456764,0.0729628744211959,0.9882554051138235],[1,12.499092105418178,-10.868886925331646,7.262315334645495]],[3,"ClothFront3_M",90,[[2,"ClothFront3_end_M",-125,[0,"9bKB9Bbi5dra4/xtTPtBWx",null,null,null,1,0],[1,0.4376417100429535,-6.428990911681864e-13,1.4210854397564648e-16]]],[0,"50cmLuKglWYpmP2JHI+fSW",null,null,null,1,0],[1,0.7495574355125427,-5.940137027008949e-14,1.4210854397564648e-16],[3,0.10204170100972755,-0.08717130296916067,0.0720363348063662,0.9883316354652245],[1,12.470913312926134,-10.864008495610268,7.157735479118148]],[3,"ArmorHip3_R",18,[[2,"ArmorHip3_end_R",-126,[0,"1aFEdGo0Nf45SV/tf/w/Ze",null,null,null,1,0],[1,2.261204719543457,-1.1368683941568192e-14,9.94759834299305e-16]]],[0,"37akLJ8wNb2allN+j0Q3K9",null,null,null,1,0],[1,0.8002017140388489,0.1026003360748291,-3.552713678800501e-14],[3,0.012431912871444536,-0.0030209081731573375,0.04179378537059301,0.99904434394103],[1,1.4428813235025801,-0.4068006081122078,4.785898044244175]],[1,"ClothBack1_M",2,[-127],[0,"4a/iscKBFUeIQR4cWSrgUn",null,null,null,1,0],[1,0.32717472314834595,-0.5598066449165344,-2.8421708795129297e-16],[3,0.0000040401932536958095,-0.00006324051299814953,0.9991232068813606,-0.041866615046121616],[1,179.99275350453507,-179.99984027414686,-4.798963353785223]],[1,"ClothBack2_M",93,[-128],[0,"adsoHM44dd4JpTel6in98W",null,null,null,1,0],[1,0.7522051334381104,-1.7053025277077578e-15,4.2632563192693945e-16],[3,0.00006296603443104618,-0.000009429091598603962,0.0008600855821921399,0.9999996280995118],[1,0.007216313380880804,-0.0010867013533913791,0.09855849167642695]],[9,"ClothBack3_M",94,[[2,"ClothBack3_end_M",-129,[0,"abeMOrl7xS8IQrg4QvTgU5",null,null,null,1,0],[1,0.44981274008750916,-1.140278951990148e-12,-2.8421708795129297e-16]]],[0,"6cQkkFYJhV/pRKpq9jHlF7",null,null,null,1,0],[1,0.7424449324607849,2.77964310639936e-13,-1.4210854397564648e-16]],[3,"RopeFront_M",2,[[2,"RopeFront_end_M",-130,[0,"28bwMAouVUApP0SxWk7/5d",null,null,null,1,0],[1,0.3364955484867096,0,6.750155905017657e-16]]],[0,"f3e8LtZHZcvK7B58kzOXe/",null,null,null,1,0],[1,0.30763378739356995,0.7486594915390015,0],[3,-0.706973695911702,0.013718355912729959,-0.013718355912729959,0.706973695911702],[1,-90.00000000000001,0,-2.2232942231949755]],[3,"RopeBack_M",2,[[2,"RopeBack_end_M",-131,[0,"ac0KoS8aZXxZxAp0er5qd0",null,null,null,1,0],[1,0.3364955484867096,1.4210854397564648e-16,2.8421708795129297e-16]]],[0,"92rjHe6Phae698DQXkOkuB",null,null,null,1,0],[1,0.3380778431892395,-0.7093393802642822,-1.1368683518051719e-15],[3,-0.706973695911702,0.013718355912729959,-0.013718355912729959,0.706973695911702],[1,-90.00000000000001,0,-2.2232942231949755]],[3,"RopeSide_R",2,[[2,"RopeSide_end_R",-132,[0,"6dGtiGxzRft5VUodeZuyCU",null,null,null,1,0],[1,0.3364955484867096,1.7053025277077578e-15,-4.2632563192693945e-16]]],[0,"b5l+o7QJ9UDZgW1USj0fin",null,null,null,1,0],[1,0.3666665256023407,0.027040086686611176,-0.8879576921463013],[3,-0.706973695911702,0.013718355912729959,-0.013718355912729959,0.706973695911702],[1,-90.00000000000001,0,-2.2232942231949755]],[1,"Hip_L",2,[-133],[0,"66H2htNCJcaJ0hBaZH7Hdr",null,null,null,1,0],[1,-0.36726757884025574,-0.08317771553993225,0.47659024596214294],[3,0.8289587977951601,-0.5121829438182851,-0.16032103970194847,-0.15745827335686305],[1,-135.03169681665605,45.21290697889535,-53.003223425567796]],[1,"Knee_L",99,[-134],[0,"64svdKHilYirO4noHRdQCV",null,null,null,1,0],[1,-1.5957510471343994,-2.842170985392048e-15,2.1316281596346973e-16],[3,6.94160547844609e-18,1.201695085370373e-17,-0.5001953895373249,0.865912566189915],[1,2.757313926086682e-15,3.1830429006591197e-15,-60.02585541975826]],[1,"Ankle_L",100,[-135],[0,"0978k5eeRcr5ocI9hakVfg",null,null,null,1,0],[1,-1.8425168991088867,5.684341759025859e-16,-5.186962106574003e-15],[3,-0.07575623868624792,0.07186217029426226,0.013230080095050336,0.994445466459267],[1,-8.777081835013174,8.334255621484989,0.8838322419895376]],[3,"Toes_L",101,[[2,"ToesEnd_L",-136,[0,"a76x4TUjdYaYxAJ4TcsJya",null,null,null,1,0],[1,-0.7260444164276123,3.930189464821407e-16,-2.8421708795129297e-16]]],[0,"e573vNS4VWmI40KTN8r+RL",null,null,null,1,0],[1,-0.5844144821166992,-0.5703486800193787,-1.6555645201109248e-14],[3,-0.026083944688472346,0.026365848584719673,0.6969574180147661,0.7161527960792213],[1,-69.8871447790152,69.91000485476566,85.47322255744105]],[3,"ArmorHip3_L",20,[[2,"ArmorHip3_end_L",-137,[0,"a2mKnGg4BbOY5gMcqWT/wF",null,null,null,1,0],[1,-2.261204719543457,7.389644180854499e-15,8.526512638538789e-16]]],[0,"66e1RdM6ZZRrXgT9r2bPFg",null,null,null,1,0],[1,-0.8002017140388489,-0.1026003360748291,3.652189566939225e-14],[3,0.010182258485906596,-0.014288205390873911,0.03364304391313243,0.9992798979240467],[1,1.2238832504525758,-1.6793909750755696,3.8386322334283385]],[3,"RopeSide_L",2,[[2,"RopeSide_end_L",-138,[0,"f0yIN5o45QtK1FuHoVN/02",null,null,null,1,0],[1,-0.3364955484867096,-8.526512638538789e-16,2.8421708795129297e-16]]],[0,"cctQsmkQNbR691PCVcqVvJ",null,null,null,1,0],[1,0.3666665256023407,0.027040086686611176,0.8879576921463013],[3,0.013718355912729959,0.706973695911702,-0.706973695911702,-0.013718355912729959],[1,90,180,2.2232942231949755]],[15,"TI_model_weapon_700_main_shared",7,[[16,-139,[10,"aeKDU4nq1Ys7WPzSZ8rC5N"],[0],[17],1,1,2]],[0,"d2MHzOOoZcQqi9kptz61m4",null,null,null,1,0]],[15,"TI_model_hero_700_main_shared",7,[[16,-140,[10,"ecRj/ICRNRvIqcCzcYUmrf"],[3],[17],1,4,5]],[0,"32MJYLxkVdcpKtceLoI9zL",null,null,null,1,0]]],0,[0,6,1,0,1,1,0,-1,7,0,-1,22,0,-2,85,0,-3,89,0,-4,17,0,-5,93,0,-6,96,0,-7,97,0,-8,98,0,-9,99,0,-10,19,0,-11,104,0,-1,59,0,-2,62,0,-3,65,0,-4,15,0,-5,6,0,0,4,0,-2,24,0,-3,29,0,-4,33,0,-1,40,0,-2,43,0,-3,46,0,-4,11,0,0,6,0,-2,74,0,-3,75,0,-4,79,0,-1,21,0,-2,105,0,-3,106,0,-1,23,0,-2,9,0,-3,13,0,-1,38,0,-2,12,0,-1,39,0,-2,55,0,-1,49,0,-2,52,0,0,12,0,-2,56,0,-1,57,0,-2,16,0,-1,58,0,-2,83,0,-1,68,0,-2,71,0,0,16,0,-2,84,0,0,17,0,-2,18,0,0,18,0,-2,92,0,0,19,0,-2,20,0,0,20,0,-2,103,0,-1,25,0,-1,26,0,-1,27,0,-1,28,0,0,28,0,-1,30,0,-1,31,0,-1,32,0,0,32,0,-1,34,0,-1,35,0,-1,36,0,-1,37,0,0,37,0,-1,41,0,-1,42,0,0,42,0,-1,44,0,-1,45,0,0,45,0,-1,47,0,-1,48,0,0,48,0,-1,50,0,-1,51,0,0,51,0,-1,53,0,-1,54,0,0,54,0,0,55,0,0,56,0,-1,60,0,-1,61,0,0,61,0,-1,63,0,-1,64,0,0,64,0,-1,66,0,-1,67,0,0,67,0,-1,69,0,-1,70,0,0,70,0,-1,72,0,-1,73,0,0,73,0,0,74,0,-1,76,0,-1,77,0,-1,78,0,0,78,0,-1,80,0,-1,81,0,-1,82,0,0,82,0,0,83,0,0,84,0,-1,86,0,-1,87,0,-1,88,0,0,88,0,-1,90,0,-1,91,0,0,91,0,0,92,0,-1,94,0,-1,95,0,0,95,0,0,96,0,0,97,0,0,98,0,-1,100,0,-1,101,0,-1,102,0,0,102,0,0,103,0,0,104,0,1,105,0,1,106,0,7,1,2,0,21,3,0,58,4,0,23,5,0,39,8,0,22,10,0,38,14,0,57,140],[0,0,0,0,0,0,0,0],[-1,4,5,-1,4,5,-1,8],[4,5,6,7,8,9,1,1]],[[[11,"Skin-1",4068526812,["Group/DeformationSystem/Root_M","Group/DeformationSystem/Root_M/Spine1_M","Group/DeformationSystem/Root_M/Spine1_M/Chest_M","Group/DeformationSystem/Root_M/Spine1_M/Chest_M/Neck_M","Group/DeformationSystem/Root_M/Spine1_M/Chest_M/Neck_M/Head_M","Group/DeformationSystem/Root_M/Spine1_M/Chest_M/Neck_M/Head_M/HeadEnd_M","Group/DeformationSystem/Root_M/Spine1_M/Chest_M/Neck_M/Head_M/HairSide1_R","Group/DeformationSystem/Root_M/Spine1_M/Chest_M/Neck_M/Head_M/HairSide1_R/HairSide2_R","Group/DeformationSystem/Root_M/Spine1_M/Chest_M/Neck_M/Head_M/HairSide1_R/HairSide2_R/HairSide3_R","Group/DeformationSystem/Root_M/Spine1_M/Chest_M/Neck_M/Head_M/HairSide1_R/HairSide2_R/HairSide3_R/HairSide4_R","Group/DeformationSystem/Root_M/Spine1_M/Chest_M/Neck_M/Head_M/HairSide1_R/HairSide2_R/HairSide3_R/HairSide4_R/HairSide5_R","Group/DeformationSystem/Root_M/Spine1_M/Chest_M/Neck_M/Head_M/HairSide1_R/HairSide2_R/HairSide3_R/HairSide4_R/HairSide5_R/HairSide5_end_R","Group/DeformationSystem/Root_M/Spine1_M/Chest_M/Neck_M/Head_M/HairBack1_M","Group/DeformationSystem/Root_M/Spine1_M/Chest_M/Neck_M/Head_M/HairBack1_M/HairBack2_M","Group/DeformationSystem/Root_M/Spine1_M/Chest_M/Neck_M/Head_M/HairBack1_M/HairBack2_M/HairBack3_M","Group/DeformationSystem/Root_M/Spine1_M/Chest_M/Neck_M/Head_M/HairBack1_M/HairBack2_M/HairBack3_M/HairBack4_M","Group/DeformationSystem/Root_M/Spine1_M/Chest_M/Neck_M/Head_M/HairBack1_M/HairBack2_M/HairBack3_M/HairBack4_M/HairBack4_end_M","Group/DeformationSystem/Root_M/Spine1_M/Chest_M/Neck_M/Head_M/HairSide1_L","Group/DeformationSystem/Root_M/Spine1_M/Chest_M/Neck_M/Head_M/HairSide1_L/HairSide2_L","Group/DeformationSystem/Root_M/Spine1_M/Chest_M/Neck_M/Head_M/HairSide1_L/HairSide2_L/HairSide3_L","Group/DeformationSystem/Root_M/Spine1_M/Chest_M/Neck_M/Head_M/HairSide1_L/HairSide2_L/HairSide3_L/HairSide4_L","Group/DeformationSystem/Root_M/Spine1_M/Chest_M/Neck_M/Head_M/HairSide1_L/HairSide2_L/HairSide3_L/HairSide4_L/HairSide5_L","Group/DeformationSystem/Root_M/Spine1_M/Chest_M/Neck_M/Head_M/HairSide1_L/HairSide2_L/HairSide3_L/HairSide4_L/HairSide5_L/HairSide5_end_L","Group/DeformationSystem/Root_M/Spine1_M/Chest_M/Scapula_R","Group/DeformationSystem/Root_M/Spine1_M/Chest_M/Scapula_R/Shoulder_R","Group/DeformationSystem/Root_M/Spine1_M/Chest_M/Scapula_R/Shoulder_R/Elbow_R","Group/DeformationSystem/Root_M/Spine1_M/Chest_M/Scapula_R/Shoulder_R/Elbow_R/ElbowPart1_R","Group/DeformationSystem/Root_M/Spine1_M/Chest_M/Scapula_R/Shoulder_R/Elbow_R/ElbowPart1_R/Wrist_R","Group/DeformationSystem/Root_M/Spine1_M/Chest_M/Scapula_R/Shoulder_R/Elbow_R/ElbowPart1_R/Wrist_R/MiddleFinger1_R","Group/DeformationSystem/Root_M/Spine1_M/Chest_M/Scapula_R/Shoulder_R/Elbow_R/ElbowPart1_R/Wrist_R/MiddleFinger1_R/MiddleFinger2_R","Group/DeformationSystem/Root_M/Spine1_M/Chest_M/Scapula_R/Shoulder_R/Elbow_R/ElbowPart1_R/Wrist_R/MiddleFinger1_R/MiddleFinger2_R/MiddleFinger3_R","Group/DeformationSystem/Root_M/Spine1_M/Chest_M/Scapula_R/Shoulder_R/Elbow_R/ElbowPart1_R/Wrist_R/MiddleFinger1_R/MiddleFinger2_R/MiddleFinger3_R/MiddleFinger4_R","Group/DeformationSystem/Root_M/Spine1_M/Chest_M/Scapula_R/Shoulder_R/Elbow_R/ElbowPart1_R/Wrist_R/ThumbFinger1_R","Group/DeformationSystem/Root_M/Spine1_M/Chest_M/Scapula_R/Shoulder_R/Elbow_R/ElbowPart1_R/Wrist_R/ThumbFinger1_R/ThumbFinger2_R","Group/DeformationSystem/Root_M/Spine1_M/Chest_M/Scapula_R/Shoulder_R/Elbow_R/ElbowPart1_R/Wrist_R/ThumbFinger1_R/ThumbFinger2_R/ThumbFinger3_R","Group/DeformationSystem/Root_M/Spine1_M/Chest_M/Scapula_R/Shoulder_R/Elbow_R/ElbowPart1_R/Wrist_R/ThumbFinger1_R/ThumbFinger2_R/ThumbFinger3_R/ThumbFinger4_R","Group/DeformationSystem/Root_M/Spine1_M/Chest_M/Scapula_R/Shoulder_R/Elbow_R/ElbowPart1_R/Wrist_R/IndexFinger1_R","Group/DeformationSystem/Root_M/Spine1_M/Chest_M/Scapula_R/Shoulder_R/Elbow_R/ElbowPart1_R/Wrist_R/IndexFinger1_R/IndexFinger2_R","Group/DeformationSystem/Root_M/Spine1_M/Chest_M/Scapula_R/Shoulder_R/Elbow_R/ElbowPart1_R/Wrist_R/IndexFinger1_R/IndexFinger2_R/IndexFinger3_R","Group/DeformationSystem/Root_M/Spine1_M/Chest_M/Scapula_R/Shoulder_R/Elbow_R/ElbowPart1_R/Wrist_R/IndexFinger1_R/IndexFinger2_R/IndexFinger3_R/IndexFinger4_R","Group/DeformationSystem/Root_M/Spine1_M/Chest_M/Scapula_R/Shoulder_R/Elbow_R/ElbowPart1_R/Wrist_R/Cup_R","Group/DeformationSystem/Root_M/Spine1_M/Chest_M/Scapula_R/Shoulder_R/Elbow_R/ElbowPart1_R/Wrist_R/Cup_R/PinkyFinger1_R","Group/DeformationSystem/Root_M/Spine1_M/Chest_M/Scapula_R/Shoulder_R/Elbow_R/ElbowPart1_R/Wrist_R/Cup_R/PinkyFinger1_R/PinkyFinger2_R","Group/DeformationSystem/Root_M/Spine1_M/Chest_M/Scapula_R/Shoulder_R/Elbow_R/ElbowPart1_R/Wrist_R/Cup_R/PinkyFinger1_R/PinkyFinger2_R/PinkyFinger3_R","Group/DeformationSystem/Root_M/Spine1_M/Chest_M/Scapula_R/Shoulder_R/Elbow_R/ElbowPart1_R/Wrist_R/Cup_R/PinkyFinger1_R/PinkyFinger2_R/PinkyFinger3_R/PinkyFinger4_R","Group/DeformationSystem/Root_M/Spine1_M/Chest_M/Scapula_R/Shoulder_R/Elbow_R/ElbowPart1_R/Wrist_R/Cup_R/RingFinger1_R","Group/DeformationSystem/Root_M/Spine1_M/Chest_M/Scapula_R/Shoulder_R/Elbow_R/ElbowPart1_R/Wrist_R/Cup_R/RingFinger1_R/RingFinger2_R","Group/DeformationSystem/Root_M/Spine1_M/Chest_M/Scapula_R/Shoulder_R/Elbow_R/ElbowPart1_R/Wrist_R/Cup_R/RingFinger1_R/RingFinger2_R/RingFinger3_R","Group/DeformationSystem/Root_M/Spine1_M/Chest_M/Scapula_R/Shoulder_R/Elbow_R/ElbowPart1_R/Wrist_R/Cup_R/RingFinger1_R/RingFinger2_R/RingFinger3_R/RingFinger4_R","Group/DeformationSystem/Root_M/Spine1_M/Chest_M/Scapula_R/ArmorShoulder1_R","Group/DeformationSystem/Root_M/Spine1_M/Chest_M/Scapula_R/ArmorShoulder1_R/ArmorShoulder1_end_R","Group/DeformationSystem/Root_M/Spine1_M/Chest_M/Scapula_R/ArmorShoulder1_R/ArmorShoulder2_R","Group/DeformationSystem/Root_M/Spine1_M/Chest_M/Scapula_R/ArmorShoulder1_R/ArmorShoulder2_R/ArmorShoulder2_end_R","Group/DeformationSystem/Root_M/Spine1_M/Chest_M/Scapula_L","Group/DeformationSystem/Root_M/Spine1_M/Chest_M/Scapula_L/Shoulder_L","Group/DeformationSystem/Root_M/Spine1_M/Chest_M/Scapula_L/Shoulder_L/Elbow_L","Group/DeformationSystem/Root_M/Spine1_M/Chest_M/Scapula_L/Shoulder_L/Elbow_L/ElbowPart1_L","Group/DeformationSystem/Root_M/Spine1_M/Chest_M/Scapula_L/Shoulder_L/Elbow_L/ElbowPart1_L/Wrist_L","Group/DeformationSystem/Root_M/Spine1_M/Chest_M/Scapula_L/Shoulder_L/Elbow_L/ElbowPart1_L/Wrist_L/MiddleFinger1_L","Group/DeformationSystem/Root_M/Spine1_M/Chest_M/Scapula_L/Shoulder_L/Elbow_L/ElbowPart1_L/Wrist_L/MiddleFinger1_L/MiddleFinger2_L","Group/DeformationSystem/Root_M/Spine1_M/Chest_M/Scapula_L/Shoulder_L/Elbow_L/ElbowPart1_L/Wrist_L/MiddleFinger1_L/MiddleFinger2_L/MiddleFinger3_L","Group/DeformationSystem/Root_M/Spine1_M/Chest_M/Scapula_L/Shoulder_L/Elbow_L/ElbowPart1_L/Wrist_L/MiddleFinger1_L/MiddleFinger2_L/MiddleFinger3_L/MiddleFinger4_L","Group/DeformationSystem/Root_M/Spine1_M/Chest_M/Scapula_L/Shoulder_L/Elbow_L/ElbowPart1_L/Wrist_L/ThumbFinger1_L","Group/DeformationSystem/Root_M/Spine1_M/Chest_M/Scapula_L/Shoulder_L/Elbow_L/ElbowPart1_L/Wrist_L/ThumbFinger1_L/ThumbFinger2_L","Group/DeformationSystem/Root_M/Spine1_M/Chest_M/Scapula_L/Shoulder_L/Elbow_L/ElbowPart1_L/Wrist_L/ThumbFinger1_L/ThumbFinger2_L/ThumbFinger3_L","Group/DeformationSystem/Root_M/Spine1_M/Chest_M/Scapula_L/Shoulder_L/Elbow_L/ElbowPart1_L/Wrist_L/ThumbFinger1_L/ThumbFinger2_L/ThumbFinger3_L/ThumbFinger4_L","Group/DeformationSystem/Root_M/Spine1_M/Chest_M/Scapula_L/Shoulder_L/Elbow_L/ElbowPart1_L/Wrist_L/IndexFinger1_L","Group/DeformationSystem/Root_M/Spine1_M/Chest_M/Scapula_L/Shoulder_L/Elbow_L/ElbowPart1_L/Wrist_L/IndexFinger1_L/IndexFinger2_L","Group/DeformationSystem/Root_M/Spine1_M/Chest_M/Scapula_L/Shoulder_L/Elbow_L/ElbowPart1_L/Wrist_L/IndexFinger1_L/IndexFinger2_L/IndexFinger3_L","Group/DeformationSystem/Root_M/Spine1_M/Chest_M/Scapula_L/Shoulder_L/Elbow_L/ElbowPart1_L/Wrist_L/IndexFinger1_L/IndexFinger2_L/IndexFinger3_L/IndexFinger4_L","Group/DeformationSystem/Root_M/Spine1_M/Chest_M/Scapula_L/Shoulder_L/Elbow_L/ElbowPart1_L/Wrist_L/Cup_L","Group/DeformationSystem/Root_M/Spine1_M/Chest_M/Scapula_L/Shoulder_L/Elbow_L/ElbowPart1_L/Wrist_L/Cup_L/PinkyFinger1_L","Group/DeformationSystem/Root_M/Spine1_M/Chest_M/Scapula_L/Shoulder_L/Elbow_L/ElbowPart1_L/Wrist_L/Cup_L/PinkyFinger1_L/PinkyFinger2_L","Group/DeformationSystem/Root_M/Spine1_M/Chest_M/Scapula_L/Shoulder_L/Elbow_L/ElbowPart1_L/Wrist_L/Cup_L/PinkyFinger1_L/PinkyFinger2_L/PinkyFinger3_L","Group/DeformationSystem/Root_M/Spine1_M/Chest_M/Scapula_L/Shoulder_L/Elbow_L/ElbowPart1_L/Wrist_L/Cup_L/PinkyFinger1_L/PinkyFinger2_L/PinkyFinger3_L/PinkyFinger4_L","Group/DeformationSystem/Root_M/Spine1_M/Chest_M/Scapula_L/Shoulder_L/Elbow_L/ElbowPart1_L/Wrist_L/Cup_L/RingFinger1_L","Group/DeformationSystem/Root_M/Spine1_M/Chest_M/Scapula_L/Shoulder_L/Elbow_L/ElbowPart1_L/Wrist_L/Cup_L/RingFinger1_L/RingFinger2_L","Group/DeformationSystem/Root_M/Spine1_M/Chest_M/Scapula_L/Shoulder_L/Elbow_L/ElbowPart1_L/Wrist_L/Cup_L/RingFinger1_L/RingFinger2_L/RingFinger3_L","Group/DeformationSystem/Root_M/Spine1_M/Chest_M/Scapula_L/Shoulder_L/Elbow_L/ElbowPart1_L/Wrist_L/Cup_L/RingFinger1_L/RingFinger2_L/RingFinger3_L/RingFinger4_L","Group/DeformationSystem/Root_M/Spine1_M/Chest_M/Scapula_L/ArmorShoulder1_L","Group/DeformationSystem/Root_M/Spine1_M/Chest_M/Scapula_L/ArmorShoulder1_L/ArmorShoulder1_end_L","Group/DeformationSystem/Root_M/Spine1_M/Chest_M/Scapula_L/ArmorShoulder1_L/ArmorShoulder2_L","Group/DeformationSystem/Root_M/Spine1_M/Chest_M/Scapula_L/ArmorShoulder1_L/ArmorShoulder2_L/ArmorShoulder2_end_L","Group/DeformationSystem/Root_M/Hip_R","Group/DeformationSystem/Root_M/Hip_R/Knee_R","Group/DeformationSystem/Root_M/Hip_R/Knee_R/Ankle_R","Group/DeformationSystem/Root_M/Hip_R/Knee_R/Ankle_R/Toes_R","Group/DeformationSystem/Root_M/Hip_R/Knee_R/Ankle_R/Toes_R/ToesEnd_R","Group/DeformationSystem/Root_M/ClothFront1_M","Group/DeformationSystem/Root_M/ClothFront1_M/ClothFront2_M","Group/DeformationSystem/Root_M/ClothFront1_M/ClothFront2_M/ClothFront3_M","Group/DeformationSystem/Root_M/ClothFront1_M/ClothFront2_M/ClothFront3_M/ClothFront3_end_M","Group/DeformationSystem/Root_M/ArmorHip1_R","Group/DeformationSystem/Root_M/ArmorHip1_R/ArmorHip1_end_R","Group/DeformationSystem/Root_M/ArmorHip1_R/ArmorHip2_R","Group/DeformationSystem/Root_M/ArmorHip1_R/ArmorHip2_R/ArmorHip2_end_R","Group/DeformationSystem/Root_M/ArmorHip1_R/ArmorHip2_R/ArmorHip3_R","Group/DeformationSystem/Root_M/ArmorHip1_R/ArmorHip2_R/ArmorHip3_R/ArmorHip3_end_R","Group/DeformationSystem/Root_M/ClothBack1_M","Group/DeformationSystem/Root_M/ClothBack1_M/ClothBack2_M","Group/DeformationSystem/Root_M/ClothBack1_M/ClothBack2_M/ClothBack3_M","Group/DeformationSystem/Root_M/ClothBack1_M/ClothBack2_M/ClothBack3_M/ClothBack3_end_M","Group/DeformationSystem/Root_M/RopeFront_M","Group/DeformationSystem/Root_M/RopeFront_M/RopeFront_end_M","Group/DeformationSystem/Root_M/RopeBack_M","Group/DeformationSystem/Root_M/RopeBack_M/RopeBack_end_M","Group/DeformationSystem/Root_M/RopeSide_R","Group/DeformationSystem/Root_M/RopeSide_R/RopeSide_end_R","Group/DeformationSystem/Root_M/Hip_L","Group/DeformationSystem/Root_M/Hip_L/Knee_L","Group/DeformationSystem/Root_M/Hip_L/Knee_L/Ankle_L","Group/DeformationSystem/Root_M/Hip_L/Knee_L/Ankle_L/Toes_L","Group/DeformationSystem/Root_M/Hip_L/Knee_L/Ankle_L/Toes_L/ToesEnd_L","Group/DeformationSystem/Root_M/ArmorHip1_L","Group/DeformationSystem/Root_M/ArmorHip1_L/ArmorHip1_end_L","Group/DeformationSystem/Root_M/ArmorHip1_L/ArmorHip2_L","Group/DeformationSystem/Root_M/ArmorHip1_L/ArmorHip2_L/ArmorHip2_end_L","Group/DeformationSystem/Root_M/ArmorHip1_L/ArmorHip2_L/ArmorHip3_L","Group/DeformationSystem/Root_M/ArmorHip1_L/ArmorHip2_L/ArmorHip3_L/ArmorHip3_end_L","Group/DeformationSystem/Root_M/RopeSide_L","Group/DeformationSystem/Root_M/RopeSide_L/RopeSide_end_L"],[[[7,6.118623227319224e-17,-6.360778035538407e-17,1,0,0.9992470145225525,-0.038794100284576416,-6.360779359027387e-17,0,0.038794100284576416,0.9992470145225525,6.118624550808204e-17,0,-4.340580463409424,0.17000021040439606,2.7639720037290246e-16,1],[7,6.123197205234397e-17,-6.101771242135803e-17,1,0,0.9999939799308777,0.003505330067127943,-6.101769918646823e-17,0,-0.003505330067127943,0.9999939799308777,6.123196543489907e-17,0,-4.936511993408203,-0.038831811398267746,2.9990284111524213e-16,1],[7,6.055841542315429e-17,-5.217270321855301e-17,1,0,0.9889940023422241,0.1479550004005432,-5.217270983599791e-17,0,-0.1479550004005432,0.9889940023422241,6.055842204059919e-17,0,-5.6158976554870605,-0.8592739701271057,2.9525930061927565e-16,1],[7,5.848147740159694e-17,-7.937955368559385e-17,1,0,0.9550750255584717,-0.29636600613594055,-7.937951398092444e-17,0,0.29636600613594055,0.9550750255584717,5.848144431437244e-17,0,-6.346978187561035,2.1071362495422363,5.384435979765081e-16,1],[7,6.123234262925839e-17,-6.123234262925839e-17,1,0,1,3.7493993930529855e-33,-6.123234262925839e-17,0,0,1,6.123234262925839e-17,0,-7.280981540679932,-0.05308070033788681,4.4258127944571315e-16,1],[7,6.123234262925839e-17,-6.123234262925839e-17,1,0,1,3.7493993930529855e-33,-6.123234262925839e-17,0,0,1,6.123234262925839e-17,0,-9.347314834594727,-0.05308070033788681,5.691076729747715e-16,1],[7,-0.25252437591552734,0.012756154872477055,0.9675059914588928,0,-0.9573988914489746,0.14145398139953613,-0.25175100564956665,0,-0.14006900787353516,-0.9898629784584045,-0.023507826030254364,0,7.912755489349365,-1.844083309173584,2.4327352046966553,1],[7,-0.19087190926074982,0.18008491396903992,-0.9649550318717957,0,-0.7390850782394409,0.6205690503120422,0.26200780272483826,0,0.6460049152374268,0.7631930112838745,0.014648874290287495,0,5.98994779586792,-3.9869539737701416,-2.5158298015594482,1],[7,0.04694894701242447,0.030966944992542267,-0.9984170198440552,0,-0.3426826596260071,0.9393609762191772,0.01302114874124527,0,0.9382771253585815,0.3415290117263794,0.05471384525299072,0,2.823403835296631,-6.512921333312988,-0.7567905187606812,1],[7,0.18874108791351318,0.11167079210281372,-0.975657045841217,0,-0.6262216567993164,0.7789890170097351,-0.03198205307126045,0,0.7564542889595032,0.6170140504837036,0.21695788204669952,0,4.297406196594238,-5.406214237213135,-0.46187877655029297,1],[7,0.23364785313606262,0.16110308468341827,-0.9588820934295654,0,-0.9124609231948853,0.37700802087783813,-0.15899524092674255,0,0.3358912467956543,0.9120919704437256,0.23508740961551666,0,5.947312831878662,-2.8985068798065186,0.37306681275367737,1],[7,0.23364785313606262,0.16110308468341827,-0.9588820934295654,0,-0.9124609231948853,0.37700802087783813,-0.15899524092674255,0,0.3358912467956543,0.9120919704437256,0.23508740961551666,0,5.274551868438721,-2.8985068798065186,0.37306681275367737,1],[7,2.2977313867657146e-17,-1.1799003519129893e-16,-1,0,0.375247985124588,-0.9269239902496338,1.1799008813085813e-16,0,-0.9269239902496338,-0.375247985124588,2.297732213946327e-17,0,-3.3522045612335205,7.6457905769348145,-9.79152616971434e-16,1],[7,3.049983001583484e-17,-1.1432815294164098e-16,-1,0,0.49810001254081726,-0.8671200275421143,1.1432811323697158e-16,0,-0.8671200275421143,-0.49810001254081726,3.049981678094504e-17,0,-5.596015453338623,6.947818756103516,-9.65008119664353e-16,1],[7,3.9305283441747575e-17,-1.0818437812974422e-16,-1,0,0.6419039964675903,-0.7667850255966187,1.0818437812974422e-16,0,-0.7667850255966187,-0.6419039964675903,3.9305283441747575e-17,0,-8.004035949707031,5.636384963989258,-9.243697023165781e-16,1],[7,5.19174915298008e-17,-9.369729570016811e-17,-1,0,0.847877025604248,-0.5301929712295532,9.369729570016811e-17,0,-0.5301929712295532,-0.847877025604248,5.19174915298008e-17,0,-10.769285202026367,2.419017791748047,-7.85769701157357e-16,1],[7,5.19174915298008e-17,-9.369729570016811e-17,-1,0,0.847877025604248,-0.5301929712295532,9.369729570016811e-17,0,-0.5301929712295532,-0.847877025604248,5.19174915298008e-17,0,-12.281649589538574,2.419017791748047,-8.642878554228177e-16,1],[7,-0.25252437591552734,0.012756154872477055,0.9675059914588928,0,0.9573988914489746,-0.14145398139953613,0.25175100564956665,0,0.14006900787353516,0.9898629784584045,0.023507826030254364,0,-7.912755489349365,1.844083309173584,-2.4327352046966553,1],[7,-0.19087190926074982,0.18008491396903992,-0.9649550318717957,0,0.7390850782394409,-0.6205690503120422,-0.26200780272483826,0,-0.6460049152374268,-0.7631930112838745,-0.014648874290287495,0,-5.98994779586792,3.9869539737701416,2.5158298015594482,1],[7,0.04694894701242447,0.030966944992542267,-0.9984170198440552,0,0.3426826596260071,-0.9393609762191772,-0.01302114874124527,0,-0.9382771253585815,-0.3415290117263794,-0.05471384525299072,0,-2.823403835296631,6.512921333312988,0.7567905187606812,1],[7,0.18874108791351318,0.11167079210281372,-0.975657045841217,0,0.6262216567993164,-0.7789890170097351,0.03198205307126045,0,-0.7564542889595032,-0.6170140504837036,-0.21695788204669952,0,-4.297406196594238,5.406214237213135,0.46187877655029297,1],[7,0.23364785313606262,0.16110308468341827,-0.9588820934295654,0,0.9124609231948853,-0.37700802087783813,0.15899524092674255,0,-0.3358912467956543,-0.9120919704437256,-0.23508740961551666,0,-5.947312831878662,2.8985068798065186,-0.37306681275367737,1],[7,0.23364785313606262,0.16110308468341827,-0.9588820934295654,0,0.9124609231948853,-0.37700802087783813,0.15899524092674255,0,-0.3358912467956543,-0.9120919704437256,-0.23508740961551666,0,-5.274551868438721,2.8985068798065186,-0.37306681275367737,1],[7,-0.9675840139389038,-0.17235299944877625,-0.18459399044513702,0,-0.19394910335540771,0.03896758705377579,0.9802370071411133,0,-0.16175363957881927,0.9842640161514282,-0.071132130920887,0,0.9921949505805969,-0.15200366079807281,-6.43195915222168,1],[7,-0.491851270198822,-0.031044723466038704,-0.8701260089874268,0,-0.866156816482544,-0.08427978307008743,0.4926149845123291,0,-0.08862712979316711,0.9959579706192017,0.014563530683517456,0,4.903430461883545,0.7901483774185181,-4.090714931488037,1],[7,-0.4683999717235565,0.15324197709560394,-0.870125949382782,0,-0.8358201384544373,0.24235501885414124,0.4926150441169739,0,0.28636863827705383,0.9580090045928955,0.014563646167516708,0,3.7514126300811768,-0.6443893909454346,-4.090714931488037,1],[7,-0.4683999717235565,0.15324197709560394,-0.870125949382782,0,-0.8358201384544373,0.24235501885414124,0.4926150441169739,0,0.28636863827705383,0.9580090045928955,0.014563646167516708,0,2.9771909713745117,-0.6443893909454346,-4.090714931488037,1],[7,-0.4859902262687683,0.40286704897880554,-0.7755720615386963,0,-0.8023731112480164,0.1460849642753601,0.5786679983139038,0,0.34642550349235535,0.9035249948501587,0.252253919839859,0,2.0232722759246826,0.35070809721946716,-4.217301368713379,1],[7,-0.40362003445625305,0.27591198682785034,-0.872331976890564,0,-0.8564831018447876,0.2213589996099472,0.4663010239601135,0,0.3217567205429077,0.9353460073471069,0.14696906507015228,0,1.6045676469802856,-0.2715224027633667,-4.0813188552856445,1],[7,-0.28251615166664124,0.271636039018631,-0.9199991226196289,0,-0.919353187084198,0.19708597660064697,0.34050890803337097,0,0.27381327748298645,0.9420039653778076,0.19404949247837067,0,1.926838755607605,-0.21105584502220154,-3.8481762409210205,1],[7,-0.2624936103820801,0.26938214898109436,-0.926568865776062,0,-0.9311368465423584,0.18119695782661438,0.3164670765399933,0,0.25314193964004517,0.9458339810371399,0.20326846837997437,0,1.7505470514297485,-0.17422805726528168,-3.803677558898926,1],[7,-0.2624936103820801,0.26938214898109436,-0.926568865776062,0,-0.9311368465423584,0.18119695782661438,0.3164670765399933,0,0.25314193964004517,0.9458339810371399,0.20326846837997437,0,1.424694538116455,-0.17422805726528168,-3.803677558898926,1],[7,0.08766312897205353,0.9961119890213013,0.008708393201231956,0,-0.6933905482292175,0.054740723222494125,0.7184799909591675,0,0.7152104377746582,-0.06902247667312622,0.6954929828643799,0,2.6357319355010986,2.1446475982666016,-2.9114551544189453,1],[7,0.08114024251699448,0.9966310262680054,-0.011971413157880306,0,-0.8636361956596375,0.07629812508821487,0.4983089864253998,0,0.49754366278648376,-0.030093954876065254,0.8669170141220093,0,3.0040369033813477,2.0483057498931885,-2.264921188354492,1],[7,0.08165858685970306,0.9966310262680054,-0.007645835634320974,0,-0.8888787031173706,0.07629557698965073,0.45174500346183777,0,0.450806587934494,-0.030092643573880196,0.892113983631134,0,2.851858139038086,2.048314094543457,-2.116466522216797,1],[7,0.08165858685970306,0.9966310262680054,-0.007645835634320974,0,-0.8888787031173706,0.07629557698965073,0.45174500346183777,0,0.450806587934494,-0.030092643573880196,0.892113983631134,0,2.529355764389038,2.048314094543457,-2.116466522216797,1],[7,-0.36073073744773865,0.5587958097457886,-0.7467398643493652,0,-0.7880930304527283,0.24555212259292603,0.5644580721855164,0,0.49878013134002686,0.7921180725097656,0.351805180311203,0,1.425444483757019,0.2569361627101898,-4.09972620010376,1],[7,-0.26540490984916687,0.557159960269928,-0.786850094795227,0,-0.8558822870254517,0.2395770251750946,0.4583319425582886,0,0.4438754618167877,0.7950940132141113,0.41327884793281555,0,1.70936119556427,0.26955196261405945,-3.9118926525115967,1],[7,-0.28315067291259766,0.5790612697601318,-0.7645348310470581,0,-0.8450637459754944,0.22632981836795807,0.4843980669975281,0,0.4535330832004547,0.7832388281822205,0.4252582788467407,0,1.393865704536438,0.3801686465740204,-3.935706853866577,1],[7,-0.28315067291259766,0.5790612697601318,-0.7645348310470581,0,-0.8450637459754944,0.22632981836795807,0.4843980669975281,0,0.4535330832004547,0.7832388281822205,0.4252582788467407,0,1.0815246105194092,0.3801686465740204,-3.935706853866577,1],[7,-0.4342873990535736,0.5344626307487488,-0.7250822186470032,0,-0.6791114211082458,0.3345593512058258,0.6533588767051697,0,0.5917789936065674,0.7761571407318115,0.2176647037267685,0,1.4671286344528198,0.24268317222595215,-4.29176664352417,1],[7,-0.396462619304657,-0.03270721435546875,-0.9174680113792419,0,-0.9170671701431274,0.06035430729389191,0.39413800835609436,0,0.04248197749257088,0.9976410269737244,-0.05392295494675636,0,1.8932135105133057,-0.1738908439874649,-3.89058780670166,1],[7,-0.21175599098205566,-0.03918040171265602,-0.9765369892120361,0,-0.9760969877243042,0.05850899964570999,0.20931300520896912,0,0.04893523454666138,0.997518002986908,-0.05063347890973091,0,2.3613996505737305,-0.1872110664844513,-3.499577522277832,1],[7,-0.10959324240684509,-0.03918038681149483,-0.9932039976119995,0,-0.9925130009651184,0.05850899964570999,0.10720900446176529,0,0.053910840302705765,0.997518002986908,-0.04529924318194389,0,2.4913718700408936,-0.1872110217809677,-3.259324550628662,1],[7,-0.10959324240684509,-0.03918038681149483,-0.9932039976119995,0,-0.9925130009651184,0.05850899964570999,0.10720900446176529,0,0.053910840302705765,0.997518002986908,-0.04529924318194389,0,2.269412040710449,-0.1872110217809677,-3.259324550628662,1],[7,-0.391155868768692,0.03451397642493248,-0.9196770191192627,0,-0.9064211249351501,0.15859101712703705,0.3914700150489807,0,0.15936358273029327,0.9867410063743591,-0.030749624595046043,0,1.8422518968582153,-0.5392972826957703,-3.940385580062866,1],[7,-0.32174426317214966,0.033949244767427444,-0.9462180137634277,0,-0.9329878687858582,0.1588679850101471,0.3229459822177887,0,0.16128741204738617,0.9867159724235535,-0.01944063976407051,0,1.861358880996704,-0.541826605796814,-3.8122901916503906,1],[7,-0.28758758306503296,0.03394913300871849,-0.9571520090103149,0,-0.9439741373062134,0.15886801481246948,0.289262980222702,0,0.16188107430934906,0.9867159724235535,-0.013641366735100746,0,1.7352961301803589,-0.5418270826339722,-3.752446174621582,1],[7,-0.28758758306503296,0.03394913300871849,-0.9571520090103149,0,-0.9439741373062134,0.15886801481246948,0.289262980222702,0,0.16188107430934906,0.9867159724235535,-0.013641366735100746,0,1.4768917560577393,-0.5418270826339722,-3.752446174621582,1],[7,-0.5303491950035095,-0.8477290272712708,0.009240221232175827,0,-0.8477649092674255,0.5303720235824585,-5.220526788640711e-10,0,-0.00490075396373868,-0.007833540439605713,-0.9999570250511169,0,5.21933650970459,-4.705336570739746,-0.2923891544342041,1],[7,-0.5303491950035095,-0.8477290272712708,0.009240221232175827,0,-0.8477649092674255,0.5303720235824585,-5.220526788640711e-10,0,-0.00490075396373868,-0.007833540439605713,-0.9999570250511169,0,4.521821022033691,-4.705336570739746,-0.2923891544342041,1],[7,-0.5303491950035095,-0.8477290272712708,0.009240221232175827,0,-0.8477649092674255,0.5303720235824585,-5.220526788640711e-10,0,-0.00490075396373868,-0.007833540439605713,-0.9999570250511169,0,4.680293560028076,-4.855603218078613,-0.2923891544342041,1],[7,-0.5303491950035095,-0.8477290272712708,0.009240221232175827,0,-0.8477649092674255,0.5303720235824585,-5.220526788640711e-10,0,-0.00490075396373868,-0.007833540439605713,-0.9999570250511169,0,3.385812520980835,-4.855603218078613,-0.2923891544342041,1],[7,-0.9675840139389038,-0.17235299944877625,-0.18459399044513702,0,0.19394910335540771,-0.03896758705377579,-0.9802370071411133,0,0.16175363957881927,-0.9842640161514282,0.071132130920887,0,-0.9921949505805969,0.15200366079807281,6.43195915222168,1],[7,-0.491851270198822,-0.031044723466038704,-0.8701260089874268,0,0.866156816482544,0.08427978307008743,-0.4926149845123291,0,0.08862712979316711,-0.9959579706192017,-0.014563530683517456,0,-4.903430461883545,-0.7901483774185181,4.090714931488037,1],[7,-0.4683999717235565,0.15324197709560394,-0.870125949382782,0,0.8358201384544373,-0.24235501885414124,-0.4926150441169739,0,-0.28636863827705383,-0.9580090045928955,-0.014563646167516708,0,-3.7514126300811768,0.6443893909454346,4.090714931488037,1],[7,-0.4683999717235565,0.15324197709560394,-0.870125949382782,0,0.8358201384544373,-0.24235501885414124,-0.4926150441169739,0,-0.28636863827705383,-0.9580090045928955,-0.014563646167516708,0,-2.9771909713745117,0.6443893909454346,4.090714931488037,1],[7,-0.4859902262687683,0.40286704897880554,-0.7755720615386963,0,0.8023731112480164,-0.1460849642753601,-0.5786679983139038,0,-0.34642550349235535,-0.9035249948501587,-0.252253919839859,0,-2.0232722759246826,-0.35070809721946716,4.217301368713379,1],[7,-0.40362003445625305,0.27591198682785034,-0.872331976890564,0,0.8564831018447876,-0.2213589996099472,-0.4663010239601135,0,-0.3217567205429077,-0.9353460073471069,-0.14696906507015228,0,-1.6045676469802856,0.2715224027633667,4.0813188552856445,1],[7,-0.28251615166664124,0.271636039018631,-0.9199991226196289,0,0.919353187084198,-0.19708597660064697,-0.34050890803337097,0,-0.27381327748298645,-0.9420039653778076,-0.19404949247837067,0,-1.926838755607605,0.21105584502220154,3.8481762409210205,1],[7,-0.2624936103820801,0.26938214898109436,-0.926568865776062,0,0.9311368465423584,-0.18119695782661438,-0.3164670765399933,0,-0.25314193964004517,-0.9458339810371399,-0.20326846837997437,0,-1.7505470514297485,0.17422805726528168,3.803677558898926,1],[7,-0.2624936103820801,0.26938214898109436,-0.926568865776062,0,0.9311368465423584,-0.18119695782661438,-0.3164670765399933,0,-0.25314193964004517,-0.9458339810371399,-0.20326846837997437,0,-1.424694538116455,0.17422805726528168,3.803677558898926,1],[7,0.08766312897205353,0.9961119890213013,0.008708393201231956,0,0.6933905482292175,-0.054740723222494125,-0.7184799909591675,0,-0.7152104377746582,0.06902247667312622,-0.6954929828643799,0,-2.6357319355010986,-2.1446475982666016,2.9114551544189453,1],[7,0.08114024251699448,0.9966310262680054,-0.011971413157880306,0,0.8636361956596375,-0.07629812508821487,-0.4983089864253998,0,-0.49754366278648376,0.030093954876065254,-0.8669170141220093,0,-3.0040369033813477,-2.0483057498931885,2.264921188354492,1],[7,0.08165858685970306,0.9966310262680054,-0.007645835634320974,0,0.8888787031173706,-0.07629557698965073,-0.45174500346183777,0,-0.450806587934494,0.030092643573880196,-0.892113983631134,0,-2.851858139038086,-2.048314094543457,2.116466522216797,1],[7,0.08165858685970306,0.9966310262680054,-0.007645835634320974,0,0.8888787031173706,-0.07629557698965073,-0.45174500346183777,0,-0.450806587934494,0.030092643573880196,-0.892113983631134,0,-2.529355764389038,-2.048314094543457,2.116466522216797,1],[7,-0.36073073744773865,0.5587958097457886,-0.7467398643493652,0,0.7880930304527283,-0.24555212259292603,-0.5644580721855164,0,-0.49878013134002686,-0.7921180725097656,-0.351805180311203,0,-1.425444483757019,-0.2569361627101898,4.09972620010376,1],[7,-0.26540490984916687,0.557159960269928,-0.786850094795227,0,0.8558822870254517,-0.2395770251750946,-0.4583319425582886,0,-0.4438754618167877,-0.7950940132141113,-0.41327884793281555,0,-1.70936119556427,-0.26955196261405945,3.9118926525115967,1],[7,-0.28315067291259766,0.5790612697601318,-0.7645348310470581,0,0.8450637459754944,-0.22632981836795807,-0.4843980669975281,0,-0.4535330832004547,-0.7832388281822205,-0.4252582788467407,0,-1.393865704536438,-0.3801686465740204,3.935706853866577,1],[7,-0.28315067291259766,0.5790612697601318,-0.7645348310470581,0,0.8450637459754944,-0.22632981836795807,-0.4843980669975281,0,-0.4535330832004547,-0.7832388281822205,-0.4252582788467407,0,-1.0815246105194092,-0.3801686465740204,3.935706853866577,1],[7,-0.4342873990535736,0.5344626307487488,-0.7250822186470032,0,0.6791114211082458,-0.3345593512058258,-0.6533588767051697,0,-0.5917789936065674,-0.7761571407318115,-0.2176647037267685,0,-1.4671286344528198,-0.24268317222595215,4.29176664352417,1],[7,-0.396462619304657,-0.03270721435546875,-0.9174680113792419,0,0.9170671701431274,-0.06035430729389191,-0.39413800835609436,0,-0.04248197749257088,-0.9976410269737244,0.05392295494675636,0,-1.8932135105133057,0.1738908439874649,3.89058780670166,1],[7,-0.21175599098205566,-0.03918040171265602,-0.9765369892120361,0,0.9760969877243042,-0.05850899964570999,-0.20931300520896912,0,-0.04893523454666138,-0.997518002986908,0.05063347890973091,0,-2.3613996505737305,0.1872110664844513,3.499577522277832,1],[7,-0.10959324240684509,-0.03918038681149483,-0.9932039976119995,0,0.9925130009651184,-0.05850899964570999,-0.10720900446176529,0,-0.053910840302705765,-0.997518002986908,0.04529924318194389,0,-2.4913718700408936,0.1872110217809677,3.259324550628662,1],[7,-0.10959324240684509,-0.03918038681149483,-0.9932039976119995,0,0.9925130009651184,-0.05850899964570999,-0.10720900446176529,0,-0.053910840302705765,-0.997518002986908,0.04529924318194389,0,-2.269412040710449,0.1872110217809677,3.259324550628662,1],[7,-0.391155868768692,0.03451397642493248,-0.9196770191192627,0,0.9064211249351501,-0.15859101712703705,-0.3914700150489807,0,-0.15936358273029327,-0.9867410063743591,0.030749624595046043,0,-1.8422518968582153,0.5392972826957703,3.940385580062866,1],[7,-0.32174426317214966,0.033949244767427444,-0.9462180137634277,0,0.9329878687858582,-0.1588679850101471,-0.3229459822177887,0,-0.16128741204738617,-0.9867159724235535,0.01944063976407051,0,-1.861358880996704,0.541826605796814,3.8122901916503906,1],[7,-0.28758758306503296,0.03394913300871849,-0.9571520090103149,0,0.9439741373062134,-0.15886801481246948,-0.289262980222702,0,-0.16188107430934906,-0.9867159724235535,0.013641366735100746,0,-1.7352961301803589,0.5418270826339722,3.752446174621582,1],[7,-0.28758758306503296,0.03394913300871849,-0.9571520090103149,0,0.9439741373062134,-0.15886801481246948,-0.289262980222702,0,-0.16188107430934906,-0.9867159724235535,0.013641366735100746,0,-1.4768917560577393,0.5418270826339722,3.752446174621582,1],[7,-0.5303491950035095,-0.8477290272712708,0.009240221232175827,0,0.8477649092674255,-0.5303720235824585,5.220527343752224e-10,0,0.00490075396373868,0.007833540439605713,0.9999570250511169,0,-5.21933650970459,4.705336570739746,0.2923891544342041,1],[7,-0.5303491950035095,-0.8477290272712708,0.009240221232175827,0,0.8477649092674255,-0.5303720235824585,5.220527343752224e-10,0,0.00490075396373868,0.007833540439605713,0.9999570250511169,0,-4.521821022033691,4.705336570739746,0.2923891544342041,1],[7,-0.5303491950035095,-0.8477290272712708,0.009240221232175827,0,0.8477649092674255,-0.5303720235824585,5.220527343752224e-10,0,0.00490075396373868,0.007833540439605713,0.9999570250511169,0,-4.680293560028076,4.855603218078613,0.2923891544342041,1],[7,-0.5303491950035095,-0.8477290272712708,0.009240221232175827,0,0.8477649092674255,-0.5303720235824585,5.220527343752224e-10,0,0.00490075396373868,0.007833540439605713,0.9999570250511169,0,-3.385812520980835,4.855603218078613,0.2923891544342041,1],[7,-0.15363046526908875,-0.1284409761428833,-0.9797449707984924,0,-0.9878249168395996,0.044549595564603806,0.14905698597431183,0,0.024502232670783997,0.9907159805297852,-0.13372130692005157,0,3.860886573791504,-0.14059889316558838,-1.0734214782714844,1],[7,-0.14036348462104797,-0.14282003045082092,-0.9797449111938477,0,-0.9874569177627563,-0.05205799639225006,0.1490570306777954,0,-0.07229185104370117,0.9883790016174316,-0.13372156023979187,0,2.268044948577881,0.08111120015382767,-1.073421597480774,1],[7,3.8281872116741056e-10,-0.06851209700107574,-0.9976500272750854,0,-1,4.722550173141826e-8,-3.626859701455487e-9,0,4.736303083063831e-8,0.9976500272750854,-0.06851209700107574,0,0.5844143629074097,0.12532535195350647,-0.9912824034690857,1],[7,0.005650184582918882,-0.0012524820631369948,-0.999983012676239,0,-0.02711041457951069,0.9996309876441956,-0.001405223156325519,0,0.9996160268783569,0.027117900550365448,0.005614148452877998,0,-0.37015852332115173,-0.011474783532321453,-1.0215368270874023,1],[7,0.005650184582918882,-0.0012524820631369948,-0.999983012676239,0,-0.02711041457951069,0.9996309876441956,-0.001405223156325519,0,0.9996160268783569,0.027117900550365448,0.005614148452877998,0,-1.0962029695510864,-0.011474783532321453,-1.0215368270874023,1],[7,-0.000009376094567414839,0.00013675700756721199,-1,0,-0.9985560178756714,0.05372770130634308,0.00001671018253546208,0,0.05372770130634308,0.9985560178756714,0.00013605566346086562,0,4.583314895629883,-0.895844042301178,-0.00016548669373150915,1],[7,-0.000032654021197231486,0.0000017320712686341722,-1,0,-0.9984530210494995,0.05560940131545067,0.00003269980152253993,0,0.05560940131545067,0.9984530210494995,-8.647879212730913e-8,0,3.8950109481811523,-0.9031858444213867,-0.00013518999912776053,1],[7,-0.000032654021197231486,0.0000017320712686341722,-1,0,-0.9984530210494995,0.05560940131545067,0.00003269980152253993,0,0.05560940131545067,0.9984530210494995,-8.647879212730913e-8,0,3.145453691482544,-0.9031858444213867,-0.00013518999912776053,1],[7,-0.000032654021197231486,0.0000017320712686341722,-1,0,-0.9984530210494995,0.05560940131545067,0.00003269980152253993,0,0.05560940131545067,0.9984530210494995,-8.647879212730913e-8,0,2.7078118324279785,-0.9031858444213867,-0.00013518999912776053,1],[7,-0.3281070590019226,-0.9446060061454773,0.00804892648011446,0,-0.9402209520339966,0.32738301157951355,0.09383859485387802,0,-0.0912756472826004,0.023221315816044807,-0.9955549836158752,0,4.460573673248291,-2.38517689704895,-0.402971476316452,1],[7,-0.3281070590019226,-0.9446060061454773,0.00804892648011446,0,-0.9402209520339966,0.32738301157951355,0.09383859485387802,0,-0.0912756472826004,0.023221315816044807,-0.9955549836158752,0,3.954650402069092,-2.38517689704895,-0.402971476316452,1],[7,-0.32643255591392517,-0.9451919794082642,0.007372548338025808,0,-0.940848171710968,0.3256619870662689,0.09353801608085632,0,-0.09081237018108368,0.023597415536642075,-0.9955880045890808,0,3.9170644283294678,-2.468750238418579,-0.40225154161453247,1],[7,-0.32643255591392517,-0.9451919794082642,0.007372548338025808,0,-0.940848171710968,0.3256619870662689,0.09353801608085632,0,-0.09081237018108368,0.023597415536642075,-0.9955880045890808,0,3.4597134590148926,-2.468750238418579,-0.40225154161453247,1],[7,-0.32643255591392517,-0.9451919794082642,0.007372548338025808,0,-0.940848171710968,0.3256619870662689,0.09353801608085632,0,-0.09081237018108368,0.023597415536642075,-0.9955880045890808,0,3.1168627738952637,-2.5713508129119873,-0.40225154161453247,1],[7,-0.32643255591392517,-0.9451919794082642,0.007372548338025808,0,-0.940848171710968,0.3256619870662689,0.09353801608085632,0,-0.09081237018108368,0.023597415536642075,-0.9955880045890808,0,0.8556578159332275,-2.5713508129119873,-0.40225154161453247,1],[7,0.0000027780449727288214,-0.00012670800788328052,1,0,-0.9924989938735962,0.12225499749183655,0.00001824788523663301,0,-0.12225499749183655,-0.9924989938735962,-0.0001254178787348792,0,4.590335845947266,-1.117751955986023,-0.00015437985712196678,1],[7,0.000021526509954128414,-7.972163302838453e-7,1,0,-0.9922869801521301,0.12396200001239777,0.0000214593001146568,0,-0.12396200001239777,-0.9922869801521301,0.0000018774018144540605,0,3.836202621459961,-1.1243525743484497,-0.00008556589455110952,1],[7,0.000021526509954128414,-7.972163302838453e-7,1,0,-0.9922869801521301,0.12396200001239777,0.0000214593001146568,0,-0.12396200001239777,-0.9922869801521301,0.0000018774018144540605,0,3.0937576293945312,-1.1243525743484497,-0.00008556589455110952,1],[7,0.000021526509954128414,-7.972163302838453e-7,1,0,-0.9922869801521301,0.12396200001239777,0.0000214593001146568,0,-0.12396200001239777,-0.9922869801521301,0.0000018774018144540605,0,2.6439449787139893,-1.1243525743484497,-0.00008556589455110952,1],[7,6.123234262925839e-17,-1,0,0,1,6.123234262925839e-17,0,0,0,0,1,0,-4.6222662925720215,-2.830321947372026e-16,-0.7585468292236328,1],[7,6.123234262925839e-17,-1,0,0,1,6.123234262925839e-17,0,0,0,0,1,0,-4.958762168884277,-3.036365888165187e-16,-0.7585468292236328,1],[7,6.123234262925839e-17,-1,0,0,1,6.123234262925839e-17,0,0,0,0,1,0,-4.709249496459961,-2.8835836437931725e-16,0.6971734762191772,1],[7,6.123234262925839e-17,-1,0,0,1,6.123234262925839e-17,0,0,0,0,1,0,-5.045744895935059,-3.0896275845863333e-16,0.6971734762191772,1],[7,6.123234262925839e-17,-1,0,0,1,6.123234262925839e-17,0,0,0,0,1,0,-4.709249496459961,-0.8879576325416565,-0.03976073116064072,1],[7,6.123234262925839e-17,-1,0,0,1,6.123234262925839e-17,0,0,0,0,1,0,-5.045744895935059,-0.8879576325416565,-0.03976073116064072,1],[7,-0.15363046526908875,-0.1284409761428833,-0.9797449707984924,0,0.9878249168395996,-0.044549595564603806,-0.14905698597431183,0,-0.024502232670783997,-0.9907159805297852,0.13372130692005157,0,-3.860886573791504,0.14059887826442719,1.0734214782714844,1],[7,-0.14036348462104797,-0.14282003045082092,-0.9797449111938477,0,0.9874569177627563,0.05205799639225006,-0.1490570306777954,0,0.07229185104370117,-0.9883790016174316,0.13372156023979187,0,-2.268044948577881,-0.08111121505498886,1.073421597480774,1],[7,-1.4795892289143353e-10,-0.06851209700107574,-0.9976500272750854,0,1,-5.827340032737993e-8,3.853529939590317e-9,0,-5.840050576466638e-8,-0.9976500272750854,0.06851209700107574,0,-0.5844143629074097,-0.12532535195350647,0.9912824034690857,1],[7,0.005650174804031849,-0.001252118730917573,-0.999983012676239,0,0.02711041457951069,-0.9996309876441956,0.0014048597076907754,0,-0.9996160268783569,-0.0271178986877203,-0.005614147987216711,0,0.3701585531234741,0.011474432423710823,1.0215368270874023,1],[7,0.005650174804031849,-0.001252118730917573,-0.999983012676239,0,0.02711041457951069,-0.9996309876441956,0.0014048597076907754,0,-0.9996160268783569,-0.0271178986877203,-0.005614147987216711,0,1.0962029695510864,0.011474432423710823,1.0215368270874023,1],[7,-0.3281070590019226,-0.9446060061454773,0.00804892648011446,0,0.9402209520339966,-0.32738301157951355,-0.09383859485387802,0,0.0912756472826004,-0.023221315816044807,0.9955549836158752,0,-4.460573673248291,2.38517689704895,0.402971476316452,1],[7,-0.3281070590019226,-0.9446060061454773,0.00804892648011446,0,0.9402209520339966,-0.32738301157951355,-0.09383859485387802,0,0.0912756472826004,-0.023221315816044807,0.9955549836158752,0,-3.954650402069092,2.38517689704895,0.402971476316452,1],[7,-0.32643255591392517,-0.9451919794082642,0.007372548338025808,0,0.940848171710968,-0.3256619870662689,-0.09353801608085632,0,0.09081237018108368,-0.023597415536642075,0.9955880045890808,0,-3.9170644283294678,2.468750238418579,0.40225154161453247,1],[7,-0.32643255591392517,-0.9451919794082642,0.007372548338025808,0,0.940848171710968,-0.3256619870662689,-0.09353801608085632,0,0.09081237018108368,-0.023597415536642075,0.9955880045890808,0,-3.4597134590148926,2.468750238418579,0.40225154161453247,1],[7,-0.32643255591392517,-0.9451919794082642,0.007372548338025808,0,0.940848171710968,-0.3256619870662689,-0.09353801608085632,0,0.09081237018108368,-0.023597415536642075,0.9955880045890808,0,-3.1168627738952637,2.5713508129119873,0.40225154161453247,1],[7,-0.32643255591392517,-0.9451919794082642,0.007372548338025808,0,0.940848171710968,-0.3256619870662689,-0.09353801608085632,0,0.09081237018108368,-0.023597415536642075,0.9955880045890808,0,-0.8556578159332275,2.5713508129119873,0.40225154161453247,1],[7,6.123234262925839e-17,-1,1.2246468525851679e-16,0,-1,-6.123234262925839e-17,7.498798786105971e-33,0,0,-1.2246468525851679e-16,-1,0,4.709249496459961,0.8879576325416565,0.03976073116064072,1],[7,6.123234262925839e-17,-1,1.2246468525851679e-16,0,-1,-6.123234262925839e-17,7.498798786105971e-33,0,0,-1.2246468525851679e-16,-1,0,5.045744895935059,0.8879576325416565,0.03976073116064072,1]],8,8,8,8,8,8,8,8,8,8,8,8,8,8,8,8,8,8,8,8,8,8,8,8,8,8,8,8,8,8,8,8,8,8,8,8,8,8,8,8,8,8,8,8,8,8,8,8,8,8,8,8,8,8,8,8,8,8,8,8,8,8,8,8,8,8,8,8,8,8,8,8,8,8,8,8,8,8,8,8,8,8,8,8,8,8,8,8,8,8,8,8,8,8,8,8,8,8,8,8,8,8,8,8,8,8,8,8,8,8,8,8,8,8,8,8,8,8,8,8,8]]],0,0,[],[],[]]]]
